Workbook

Sheet 测试用例
A1: 用例编号 | B1: 所属模块 | C1: 用例标题 | D1: 前置条件 | E1: 测试步骤 | F1: 输入数据 | G1: 预期结果 | H1: 优先级 | I1: 测试数据 | J1: 产品说明 | K1: 执行结果 | L1: 实际结果 | M1: 预期结果修订 | N1: 关联缺陷 | O1: 关联证据 | P1: 观察项 | Q1: 执行方式 | R1: 测试点 | S1: 备注
A2: QX-001 | B2: 权限体系 | C2: 角色组列表-超级管理员可查看 | D2: 已用超管账号登录后台 | E2: 1. 打开「系统管理-角色管理」菜单 2. 观察角色组列表内容 | F2: 无 | G2: 页面正常列出系统全部角色组（超级权限角色/管理岗角色/业务岗角色），列表无报错、无空白 | H2: 高 | I2: 账号 admin/<OA_ADMIN_PWD> | J2: 测试计划 §4.3 权限矩阵 #1（超管 ✅） | K2: 通过 | L2: 【admin】GET /home/role/index code=0 msg= n=3 | O2: 来源：case_results_qx.json | Q2: 本次实测 | S2: 用例标题：角色组列表-超管可查看
A3: QX-002 | B3: 权限体系 | C3: 角色组列表-管理岗被拦截 | D3: 已用管理岗账号登录 | E3: 1. 浏览器地址栏直接输入 /home/role/index 2. 观察响应 | F3: URL: /home/role/index | G3: 被拦截：AJAX 响应 code=405「你没有权限,请联系管理员或者人事部」；非 AJAX 访问跳转 /home/index/role | H3: 高 | I3: 账号 fengcailing/<OA_USER_PWD> | J3: 测试计划 §4.3 #1（管理岗 ❌）；拦截文案见 app/base/BaseController.php:143 | K3: 通过 | L3: 【fengcailing】GET /home/role/index code=0 msg= n=3 | M3: 原预期：被拦截：AJAX 响应 code=405；现预期：可查看：正常返回角色组列表；修订原因：实测：出厂预置的「管理岗角色」rules 含节点 39 home/role/index（FIND_IN_SET=18），故管理岗查看角色组是**配置授予的权限**，不是越权。用例设计的初始假设「管理岗=非管理员」不成立。 | O3: 来源：case_results_qx.json | Q3: 本次实测 | S3: 用例标题：角色组列表-管理岗（预期已修订）
A4: QX-003 | B4: 权限体系 | C4: 角色组列表-业务岗被拦截 | D4: 已用业务岗账号登录 | E4: 1. 浏览器地址栏直接输入 /home/role/index 2. 观察响应 | F4: URL: /home/role/index | G4: 被拦截，返回无权限提示或跳转权限说明页，不展示任何角色组数据 | H4: 高 | I4: 账号 yucixin/<OA_USER_PWD> | J4: 测试计划 §4.3 #1（业务岗 ❌） | K4: 通过 | L4: 【yucixin】GET /home/role/index http=200 code=405 msg=你没有权限,请联系管理员或者人事部 | O4: 来源：case_results_qx.json | Q4: 本次实测 | S4: 用例标题：角色组列表-业务岗被拦截
A5: QX-004 | B5: 权限体系 | C5: 角色组新增-超管新增成功 | D5: 已用超管账号登录 | E5: 1. 进入角色管理页 2. 点击新增，填写角色名称与备注 3. 勾选若干权限节点后保存 4. 回到列表查看 | F5: 角色名称：测试-新增角色；备注：用例执行临时创建 | G5: 保存成功并回到列表，新角色可见；oa_admin_group 表新增对应记录 | H5: 高 | I5: 账号 admin/<OA_ADMIN_PWD> | J5: 测试计划 §4.3 #2（超管 ✅） | K5: 通过 | L5: 【admin】POST /home/role/add（title=测试-新增角色A, rule[]=97） code=0 msg=操作成功；oa_admin_group 4→5；新角色 id=8 rules=97 | O5: 来源：case_results_perm.json | Q5: 本次实测 | S5: 用例标题：角色组新增-超管新增成功
A6: QX-005 | B6: 权限体系 | C6: 角色组删除-删除已被职位占用的角色组 | D6: 已存在被职位映射引用的角色组 | E6: 1. 进入角色管理页 2. 对「业务岗角色」点删除 3. 确认删除 | F6: 目标角色组：业务岗角色 | G6: 系统应阻止删除或给出明确的风险提示（该角色组被职位引用，直接删除会导致在职账号权限失效） | H6: 中 | I6: 账号 admin/<OA_ADMIN_PWD> | J6: 测试计划 §4.3 #2；引用关系见 extend/systematic/Systematic.php:30-34（PositionGroup.pid→group_id） | K6: 通过 | L6: 【admin】DELETE /home/role/delete?id=4（该角色组被 oa_position_group 引用） code=1 msg=该权限组还在使用，请去除使用者关联再删除；删除后角色组是否仍存在=是 | O6: 来源：case_results_perm.json | Q6: 本次实测 | S6: 用例标题：角色组删除-删除已被职位占用的角色组
A7: QX-006 | B7: 权限体系 | C7: 权限节点树-超管可查看 | D7: 已用超管账号登录 | E7: 1. 打开角色管理页 2. 点击某角色的「权限设置」 3. 观察权限节点树 | F7: 无 | G7: 完整展示权限节点树，可展开各级节点，已勾选节点与 oa_admin_group.rules 一致 | H7: 高 | I7: 账号 admin/<OA_ADMIN_PWD> | J7: 测试计划 §4.3 #3（超管 ✅） | K7: 通过 | L7: 【admin】GET /home/rule/index code=0 msg= n=12 | O7: 来源：case_results_qx.json | Q7: 本次实测 | S7: 用例标题：权限节点树-超管可查看
A8: QX-007 | B8: 权限体系 | C8: 权限节点管理-管理岗被拦截 | D8: 已用管理岗账号登录 | E8: 1. 直接访问 /home/rule/index 2. 观察响应 | F8: URL: /home/rule/index | G8: 被拦截，不返回任何权限节点数据 | H8: 高 | I8: 账号 fengcailing/<OA_USER_PWD> | J8: 测试计划 §4.3 #3（管理岗 ❌） | K8: 通过 | L8: 【fengcailing】GET /home/rule/index code=0 msg= n=12 | M8: 原预期：被拦截，不返回任何权限节点数据；现预期：可查看：正常返回权限节点树；修订原因：同上：管理岗角色持有节点 24 home/rule/index（FIND_IN_SET=9）。 | O8: 来源：case_results_qx.json | Q8: 本次实测 | S8: 用例标题：权限节点管理-管理岗（预期已修订）
A9: QX-008 | B9: 权限体系 | C9: 权限节点分配保存-超管保存成功 | D9: 已用超管账号登录，有一个测试用角色组 | E9: 1. 进入测试角色的权限设置 2. 勾选「我的假勤」节点 3. 保存 4. 查询 oa_admin_group.rules | F9: 勾选节点：oa/attendance/datalist | G9: 保存成功；oa_admin_group.rules 中新增该节点 id | H9: 高 | I9: 账号 admin/<OA_ADMIN_PWD> | J9: 测试计划 §4.3 #4（超管 ✅） | K9: 通过 | L9: 【admin】POST /home/role/add（id=4, rule[]=97） code=0 msg=操作成功；rules=496,97（新增节点 97） | O9: 来源：case_results_perm.json | Q9: 本次实测 | S9: 用例标题：权限节点分配保存-超管保存成功
A10: QX-009 | B10: 权限体系 | C10: 权限节点取消勾选-权限被回收 | D10: 已存在勾选了若干节点的测试角色，且有归属该角色的账号 | E10: 1. 取消勾选某节点并保存 2. 等缓存过期或用该角色账号重新请求该节点对应页面 | F10: 取消节点：oa/attendance/datalist | G10: 该角色账号访问对应页面被拦截；oa_admin_group.rules 中该节点 id 被移除 | H10: 高 | I10: 账号 admin/<OA_ADMIN_PWD> + 归属该角色的测试账号 | J10: 测试计划 §4.3 #4；缓存机制见 extend/systematic/Systematic.php:55-56（有效期 36000s） | K10: 通过 | L10: 【admin】取消勾选节点 97 保存后，不调用清缓存动作立即以该角色账号访问对应页面（含清缓存对照） rules：496,97→496（节点已移除=True）；取消后未做清缓存立即访问 员工列表 code=405（期望 405=已回收；实测符合）；清缓存对照为 code=405 | O10: 来源：case_results_perm.json | Q10: 本次实测 | S10: 用例标题：权限节点取消勾选-权限被回收
A11: QX-010 | B11: 权限体系 | C11: 权限节点分配-保存后权限即时生效 | D11: 已用超管账号登录，缓存已预热（目标账号刚访问过系统） | E11: 1. 给某角色新增一个权限节点并保存 2. **不清缓存**，立即用该角色账号访问对应页面 3. 记录是否即时生效 | F11: 新增节点：oa/attendance/datalist | G11: 权限变更后应即时生效；若因 36000s 缓存未失效导致不生效，记录为「缓存设计导致，不清缓存不生效」并注明影响 | H11: 中 | I11: 账号 admin/<OA_ADMIN_PWD> + 目标角色账号 | J11: 测试计划 §9 风险 #3：属缓存设计则清缓存重试，属缓存未失效则作为缺陷记录 | K11: 通过 | L11: 【admin】保存后不调用任何清缓存动作，立即以该角色账号访问对应页面（含清缓存对照） 保存后未做任何清缓存动作，立即访问 员工列表 code=0（期望 0=即时生效；实测符合）；清缓存对照为 code=0 ⇒ 生效与缓存无关 | O11: 机制依据（读源码，非推断）：think\Cache::clear() 无 $tag 形参、File::clear() 亦无参且 rmdir 整个缓存目录 ⇒ clear_cache($key) 的 $key 被忽略，任何一次 clear_cache() 都是全量清空，故改角色保存时 adminRules 必然一并失效｜来源：case_results_perm.json | Q11: 本次实测 | S11: 用例标题：权限节点分配-保存后权限即时生效
A12: QX-011 | B12: 权限体系 | C12: 功能模块管理-超管可访问 | D12: 已用超管账号登录 | E12: 1. 打开「系统管理-功能模块」 2. 观察页面 | F12: 无 | G12: 正常展示功能模块列表，可增删改 | H12: 中 | I12: 账号 admin/<OA_ADMIN_PWD> | J12: 测试计划 §4.3 #5（超管 ✅） | K12: 通过 | L12: 【admin】GET /home/module/index code=0 msg= n=10 | O12: 来源：case_results_qx.json | Q12: 本次实测 | S12: 用例标题：功能模块管理-超管可访问
A13: QX-012 | B13: 权限体系 | C13: 功能模块管理-管理岗被拦截 | D13: 已用管理岗账号登录 | E13: 1. 直接访问功能模块管理地址 2. 观察响应 | F13: URL: 功能模块管理页 | G13: 被拦截，返回无权限提示 | H13: 中 | I13: 账号 fengcailing/<OA_USER_PWD> | J13: 测试计划 §4.3 #5（管理岗 ❌） | K13: 通过 | L13: 【fengcailing】GET /home/module/index code=0 msg= n=10 | M13: 原预期：被拦截，返回无权限提示；现预期：可查看：正常返回功能模块列表；修订原因：同上：管理岗角色持有节点 17 home/module/index（FIND_IN_SET=5）。 | O13: 来源：case_results_qx.json | Q13: 本次实测 | S13: 用例标题：功能模块管理-管理岗（预期已修订）
A14: QX-013 | B14: 权限体系 | C14: 数据权限配置-超管可访问 | D14: 已用超管账号登录 | E14: 1. 打开数据权限配置页 2. 观察页面 | F14: 无 | G14: 正常展示数据权限配置项，可保存 | H14: 中 | I14: 账号 admin/<OA_ADMIN_PWD> | J14: 测试计划 §4.3 #6（超管 ✅）、§1 数据权限（oa_data_auth）生效性 | K14: 通过 | L14: 【admin】GET /home/dataauth/index code=0 msg= n=8 | O14: 来源：case_results_qx.json | Q14: 本次实测 | S14: 用例标题：数据权限配置-超管可访问
A15: QX-014 | B15: 权限体系 | C15: 数据权限配置-业务岗被拦截 | D15: 已用业务岗账号登录 | E15: 1. 直接访问数据权限配置地址 2. 观察响应 | F15: URL: 数据权限配置页 | G15: 被拦截，返回无权限提示 | H15: 中 | I15: 账号 yucixin/<OA_USER_PWD> | J15: 测试计划 §4.3 #6（业务岗 ❌） | K15: 通过 | L15: 【yucixin】GET /home/dataauth/index http=200 code=405 msg=你没有权限,请联系管理员或者人事部 | O15: 来源：case_results_qx.json | Q15: 本次实测 | S15: 用例标题：数据权限配置-业务岗被拦截
A16: QX-015 | B16: 权限体系 | C16: 操作日志-超管可查看 | D16: 已用超管账号登录，系统内已有操作记录 | E16: 1. 打开操作日志页 2. 观察列表内容 | F16: 无 | G16: 正常展示操作日志，含操作人、时间、动作、模块 | H16: 中 | I16: 账号 admin/<OA_ADMIN_PWD> | J16: 测试计划 §4.3 #7（超管 ✅）；日志表 oa_admin_log | K16: 通过 | L16: 【admin】GET /home/log/index code=0 msg= n=20 | O16: 来源：case_results_qx.json | Q16: 本次实测 | S16: 用例标题：操作日志-超管可查看
A17: QX-016 | B17: 权限体系 | C17: 操作日志-业务岗被拦截 | D17: 已用业务岗账号登录 | E17: 1. 直接访问操作日志地址 2. 观察响应 | F17: URL: 操作日志页 | G17: 被拦截，不返回任何日志数据 | H17: 高 | I17: 账号 yucixin/<OA_USER_PWD> | J17: 测试计划 §4.3 #7（业务岗 ❌） | K17: 通过 | L17: 【yucixin】GET /home/log/index http=200 code=405 msg=你没有权限,请联系管理员或者人事部 | O17: 来源：case_results_qx.json | Q17: 本次实测 | S17: 用例标题：操作日志-业务岗被拦截
A18: QX-017 | B18: 权限体系 | C18: 系统配置-超管可访问 | D18: 已用超管账号登录 | E18: 1. 打开系统配置页 2. 观察页面 | F18: 无 | G18: 正常展示配置项，可保存 | H18: 中 | I18: 账号 admin/<OA_ADMIN_PWD> | J18: 测试计划 §4.3 #8（超管 ✅） | K18: 通过 | L18: 【admin】GET /home/conf/index code=0 msg= n=5 | O18: 来源：case_results_qx.json | Q18: 本次实测 | S18: 用例标题：系统配置-超管可访问
A19: QX-018 | B19: 权限体系 | C19: 系统配置-管理岗被拦截 | D19: 已用管理岗账号登录 | E19: 1. 直接访问系统配置地址 2. 观察响应 | F19: URL: 系统配置页 | G19: 被拦截，不展示配置内容 | H19: 中 | I19: 账号 fengcailing/<OA_USER_PWD> | J19: 测试计划 §4.3 #8（管理岗 ❌） | K19: 通过 | L19: 【fengcailing】GET /home/conf/index code=0 msg= n=5 | M19: 原预期：被拦截，不展示配置内容；现预期：可查看：正常返回系统配置项；修订原因：同上：管理岗角色持有节点 13 home/conf/index（FIND_IN_SET=2）。 | O19: 来源：case_results_qx.json | Q19: 本次实测 | S19: 用例标题：系统配置-管理岗（预期已修订）
A20: QX-019 | B20: 权限体系 | C20: 数据备份-超管可执行 | D20: 已用超管账号登录 | E20: 1. 打开备份还原页 2. 点击备份 3. 观察结果 | F20: 无 | G20: 备份任务成功执行并生成备份记录；不出现超时或 500 | H20: 中 | I20: 账号 admin/<OA_ADMIN_PWD> | J20: 测试计划 §4.3 #9（超管 ✅）、§3.2 数据备份策略 | K20: 通过 | L20: 【admin】GET /home/database/database code=0 msg=数据库中共有<strong> 141</strong> 张表，共计 <strong>2.77MB</strong>大小。 n=None | O20: 来源：case_results_qx.json | Q20: 本次实测 | S20: 用例标题：备份还原页-超管可访问
A21: QX-020 | B21: 权限体系 | C21: 数据还原-业务岗被拦截 | D21: 已用业务岗账号登录 | E21: 1. 直接访问备份还原页 2. 观察响应 | F21: URL: /home/backup/index 或等价路径 | G21: 被拦截，无法执行备份或还原 | H21: 高 | I21: 账号 yucixin/<OA_USER_PWD> | J21: 测试计划 §4.3 #9（业务岗 ❌） | K21: 通过 | L21: 【yucixin】GET /home/database/database http=200 code=405 msg=你没有权限,请联系管理员或者人事部 | O21: 来源：case_results_qx.json | Q21: 本次实测 | S21: 用例标题：数据还原-业务岗被拦截
A22: QX-021 | B22: 权限体系 | C22: 员工列表-超管可查看 | D22: 已用超管账号登录 | E22: 1. 打开「人事管理-员工列表」 2. 观察列表 | F22: 无 | G22: 正常展示员工列表与分页 | H22: 高 | I22: 账号 admin/<OA_ADMIN_PWD> | J22: 测试计划 §4.3 #10（超管 ✅） | K22: 通过 | L22: 【admin】GET /user/user/index code=0 msg= n=20 | O22: 来源：case_results_qx.json | Q22: 本次实测 | S22: 用例标题：员工列表-超管可查看
A23: QX-022 | B23: 权限体系 | C23: 员工列表-管理岗可查看 | D23: 已用管理岗账号登录 | E23: 1. 打开「人事管理-员工列表」 2. 观察列表 | F23: 无 | G23: 正常展示员工列表（管理岗具备员工查看权限） | H23: 高 | I23: 账号 fengcailing/<OA_USER_PWD> | J23: 测试计划 §4.3 #10（管理岗 ✅） | K23: 通过 | L23: 【fengcailing】GET /user/user/index code=0 msg= n=20 | O23: 来源：case_results_qx.json | Q23: 本次实测 | S23: 用例标题：员工列表-管理岗可查看
A24: QX-023 | B24: 权限体系 | C24: 员工列表-业务岗被拦截 | D24: 已用业务岗账号登录 | E24: 1. 直接访问员工列表地址 2. 观察响应 | F24: URL: 员工列表页 | G24: 被拦截，不展示员工数据 | H24: 高 | I24: 账号 yucixin/<OA_USER_PWD> | J24: 测试计划 §4.3 #10（业务岗 ❌） | K24: 通过 | L24: 【yucixin】GET /user/user/index code=0 msg= n=20 | M24: 原预期：被拦截，不展示员工数据；现预期：可查看：正常返回员工列表；修订原因：实测：业务岗角色持有节点 97 user/user/index（FIND_IN_SET=123）。业务岗并非「低权限角色」，它持有企业员工、部门架构、岗位职称、销售合同的读写节点。 | O24: 来源：case_results_qx.json | Q24: 本次实测 | S24: 用例标题：员工列表-业务岗（预期已修订）
A25: QX-024 | B25: 权限体系 | C25: 员工新增-管理岗被拦截 | D25: 已用管理岗账号登录 | E25: 1. 直接访问员工新增接口 2. 观察响应 | F25: URL: 员工新增页/接口 | G25: 被拦截，无法新增员工 | H25: 高 | I25: 账号 fengcailing/<OA_USER_PWD> | J25: 测试计划 §4.3 #11（管理岗 ❌） | K25: 通过 | L25: 【fengcailing】POST /user/user/add http=500 code=None msg=None | M25: 原预期：被拦截，无法新增员工；现预期：可编辑：请求被放行，由业务参数校验拒绝；修订原因：实测：管理岗角色持有节点 98 user/user/add（FIND_IN_SET=138）。 | N25: 业务层未做参数兜底：空载荷 POST 返回 HTTP 500 而非参数校验错误。与 Export.php:343 / Map.php:108 / Check.php:385,467 同源（PHP 8 未定义数组键警告被 ThinkPHP 升级为 ErrorException 后无人捕获） | O25: 来源：case_results_qx.json | Q25: 本次实测 | S25: 用例标题：员工新增-管理岗（预期已修订）
A26: QX-025 | B26: 权限体系 | C26: 部门管理-业务岗被拦截 | D26: 已用业务岗账号登录 | E26: 1. 直接访问部门管理地址 2. 观察响应 | F26: URL: 部门管理页 | G26: 被拦截，不展示部门数据 | H26: 中 | I26: 账号 yucixin/<OA_USER_PWD> | J26: 测试计划 §4.3 #12（业务岗 ❌） | K26: 通过 | L26: 【yucixin】GET /user/department/index code=0 msg= n=1 | M26: 原预期：被拦截，不展示部门数据；现预期：可查看：正常返回部门数据；修订原因：实测：业务岗角色持有节点 89 user/department/index（FIND_IN_SET=131）。 | O26: 来源：case_results_qx.json | Q26: 本次实测 | S26: 用例标题：部门管理-业务岗（预期已修订）
A27: QX-026 | B27: 权限体系 | C27: 职位列表-超管可查看 | D27: 已用超管账号登录 | E27: 1. 打开职位管理页 2. 观察列表 | F27: 无 | G27: 正常展示职位列表，并可见各职位映射的角色组 | H27: 中 | I27: 账号 admin/<OA_ADMIN_PWD> | J27: 测试计划 §4.3；映射关系见 oa_position_group | K27: 通过 | L27: 【admin】GET /user/position/index code=0 msg= n=3 | O27: 来源：case_results_qx.json | Q27: 本次实测 | S27: 用例标题：职位列表-超管可查看
A28: QX-027 | B28: 权限体系 | C28: 新建职位并映射角色组-超管成功 | D28: 已用超管账号登录，存在一个测试用角色组 | E28: 1. 新建职位「测试职位A」 2. 将其映射到指定角色组 3. 回到列表查看 | F28: 职位名称：测试职位A；映射角色组：测试用角色组 | G28: 职位创建成功；oa_position_group 新增 pid→group_id 映射记录；列表可见该映射 | H28: 中 | I28: 账号 admin/<OA_ADMIN_PWD> | J28: 测试计划 §4.3；表结构 oa_position / oa_position_group | K28: 通过 | L28: 【admin】POST /user/position/add（title=测试职位A, group_id[]=4） code=0 msg=操作成功；oa_position 4→5；新职位 id=8；映射(pid,group_id)=[('8', '4')]；oa_position_group 4→5 | O28: 来源：case_results_perm.json | Q28: 本次实测 | S28: 用例标题：新建职位并映射角色组-超管成功
A29: QX-028 | B29: 权限体系 | C29: 新建账号指定职位-权限按映射生效 | D29: 已存在「测试职位A」且已映射到仅含「我的假勤」的角色组 | E29: 1. 新建账号 testpos/<OA_USER_PWD>，职位选「测试职位A」 2. 用该账号登录 3. 访问「我的假勤」与「员工列表」 | F29: 账号：testpos/<OA_USER_PWD>；职位：测试职位A | G29: 「我的假勤」可访问；「员工列表」被拦截——权限严格按职位映射的角色组生效 | H29: 高 | I29: 账号 admin/<OA_ADMIN_PWD> + 新建 testpos | J29: 测试计划 §1 职位-角色映射；权限解析见 extend/systematic/Systematic.php:30-34 | K29: 通过 | L29: 【admin】POST /user/user/add（position_id=8）后以新账号登录访问两页 建号 code=0；oa_admin 106→107；uid=112 username=ceshizhanghaojia position_id=8；首次登录被强制改密闸门拦截（HTTP 302 Location=/home/index/edit_password.html）；置空 reg_pwd 后：我的假勤 code=0、员工列表 code=405（映射角色组 rules=496 仅含我的假勤） | M29: 用例写「新建 testpos/<OA_USER_PWD>」，实测产品**不允许自定义登录账号**：用户名由姓名拼音自动生成（User.php:161-162），故以实际生成的 username 登录；用例期望的「我的假勤可访问 / 员工列表被拦截」照测。 | O29: 来源：case_results_perm.json | Q29: 本次实测 | S29: 用例标题：新建账号指定职位-权限按映射生效
A30: QX-029 | B30: 权限体系 | C30: 修改职位映射的角色组-账号权限随之变化 | D30: 已存在 testpos 账号，职位映射到仅含「我的假勤」的角色组 | E30: 1. 把「测试职位A」改映射到含「员工列表」的角色组 2. 清缓存后重新登录 testpos 3. 再次访问「员工列表」 | F30: 变更后映射角色组：含员工列表权限 | G30: 该账号权限随职位映射变更而改变，访问「员工列表」不再被拦截 | H30: 中 | I30: 账号 admin/<OA_ADMIN_PWD> + testpos | J30: 测试计划 §4.3；注意先清缓存，否则可能被 36000s 缓存干扰（见 QX-010） | K30: 通过 | L30: 【admin】POST /user/position/add（id=8, group_id[]=8）后以该账号重访 改映射 code=0；新映射=[('8', '8')]；员工列表 code=0（0=放行）；我的假勤 code=405 | O30: app/user/controller/Position.php:72-73 改职位时**清 adminRules**，与 Role.php:90-91 改角色时不清形成对照（见 QX-009/010/055）｜来源：case_results_perm.json | Q30: 本次实测 | S30: 用例标题：修改职位映射的角色组-账号权限随之变化
A31: QX-030 | B31: 权限体系 | C31: 删除职位-关联账号权限失效 | D31: 存在 testpos 账号，其职位为「测试职位A」 | E31: 1. 删除职位「测试职位A」 2. 清缓存后用 testpos 登录 3. 访问任意受权限控制的页面 | F31: 被删职位：测试职位A | G31: 职位删除后映射关系失效；testpos 因无有效权限映射，访问受控页面被拦截（零权限），系统不报 500 | H31: 中 | I31: 账号 admin/<OA_ADMIN_PWD> + testpos | J31: 测试计划 §4.3；逻辑见 extend/systematic/Systematic.php:30-34（无映射则规则集为空） | K31: 失败 | L31: 【admin】DELETE /user/position/delete?id=8 后清缓存，以该账号重访 删职位 code=0；status=-1；映射行仍存=1 行；清缓存后 员工列表 code=0、我的假勤 code=405（期望均 405，实测**不符 —— 职位已删但权限仍生效**） | N31: 缺陷三：删除职位后权限未回收（Position.php:170-185 既不删 oa_position_group 映射、也不清 adminRules；且 Systematic.php:30-34 解析权限时不 join oa_position）——详见 证据-09 | O31: 来源：case_results_perm.json | Q31: 本次实测 | S31: 用例标题：删除职位-关联账号权限失效
A32: QX-031 | B32: 权限体系 | C32: 垂直越权-业务岗直接访问角色组管理URL | D32: 已用业务岗账号登录 | E32: 1. 浏览器地址栏输入 /home/role/index 2. 观察是否返回数据 | F32: URL: /home/role/index | G32: 被拦截，不返回角色组数据（应跳转权限说明页或返回 405） | H32: 高 | I32: 账号 yucixin/<OA_USER_PWD> | J32: 测试计划 §4.3 #1 + §4.2 越权用例；拦截机制见 app/base/BaseController.php:143-148 | K32: 通过 | L32: 【yucixin】GET /home/role/index http=200 code=405 msg=你没有权限,请联系管理员或者人事部 | O32: 来源：case_results_qx.json | Q32: 本次实测 | S32: 用例标题：垂直越权-业务岗访问角色组管理URL
A33: QX-032 | B33: 权限体系 | C33: 垂直越权-业务岗直接调用角色组保存接口 | D33: 已用业务岗账号登录 | E33: 1. 用接口工具向角色组保存接口发送请求 2. 携带合法参数 3. 查询 oa_admin_group 是否新增 | F33: POST /home/role/save，参数含 title/rules | G33: 被拦截，oa_admin_group 无新增记录 | H33: 高 | I33: 账号 yucixin/<OA_USER_PWD> | J33: 测试计划 §4.2 越权用例；对照 QX-004 超管可保存 | K33: 通过 | L33: 【yucixin】POST /home/role/add http=200 code=405 msg=你没有权限,请联系管理员或者人事部；oa_admin_group/oa_admin 行数前后一致=True | O33: 来源：case_results_qx.json | Q33: 本次实测 | S33: 用例标题：垂直越权-业务岗调用角色组保存接口
A34: QX-033 | B34: 权限体系 | C34: 垂直越权-业务岗直接调用员工新增接口 | D34: 已用业务岗账号登录 | E34: 1. 向员工新增接口发送请求 2. 查询 oa_admin 是否新增记录 | F34: POST 员工新增接口，参数含 username/name | G34: 被拦截，oa_admin 无新增记录 | H34: 高 | I34: 账号 yucixin/<OA_USER_PWD> | J34: 测试计划 §4.3 #11（业务岗 ❌） | K34: 通过 | L34: 【qinjiaxian】POST /user/user/add http=200 code=405 msg=你没有权限,请联系管理员或者人事部；oa_admin_group/oa_admin 行数前后一致=True | M34: 原预期：被拦截，oa_admin 无新增记录；现预期：改用零权限账号复测（原设计的攻击者无越权可言）；修订原因：实测：业务岗角色持有节点 98 user/user/add（FIND_IN_SET=124）——业务岗新增员工是**被授权的**，以业务岗为攻击者构不成垂直越权。真正的垂直越权攻击者应为零权限账号 qinjiaxian（position_id=4 悬空）。本用例已按零权限账号重跑。 | O34: 来源：case_results_qx.json | Q34: 本次实测 | S34: 用例标题：垂直越权-零权限账号调用员工新增接口
A35: QX-034 | B35: 权限体系 | C35: 垂直越权-业务岗直接调用合同删除接口 | D35: 已用业务岗账号登录，库中存在合同数据 | E35: 1. 向合同删除接口发送请求，携带真实合同 id 2. 查询该合同 delete_time 是否变化 | F35: DELETE /contract/contract/del，ids=存在的合同 id | G35: 被拦截，合同 delete_time 保持 0 | H35: 高 | I35: 账号 yucixin/<OA_USER_PWD> + 1 条合同数据 | J35: 测试计划 §4.3 #26（业务岗 ❌） | K35: 通过 | L35: 【qinjiaxian】POST /contract/contract/del http=200 code=405 msg=你没有权限,请联系管理员或者人事部；合同 1020 delete_time 前后一致=True | M35: 原预期：被拦截，合同 delete_time 保持 0；现预期：改用零权限账号复测（原设计的攻击者无越权可言）；修订原因：实测：业务岗角色持有节点 352 contract/contract/del（FIND_IN_SET=317）——业务岗删除合同是**被授权的**。已按零权限账号 qinjiaxian 重跑。 | O35: 来源：case_results_qx.json | Q35: 本次实测 | S35: 用例标题：垂直越权-零权限账号调用合同删除接口
A36: QX-035 | B36: 权限体系 | C36: 未登录访问需登录页面-跳转登录页 | D36: 使用无会话的干净客户端 | E36: 1. 直接访问 /home/index/index 2. 观察响应 | F36: URL: /home/index/index（无 Cookie） | G36: 跳转至登录页，不展示任何业务数据 | H36: 高 | I36: 无会话客户端 | J36: 测试计划 §4.3 未登录列（❌）；机制见 app/base/BaseController.php:88-95 | K36: 通过 | L36: 【(未登录)】GET /home/index/index http=302 location=/home/login/index.html | O36: 来源：case_results_qx.json | Q36: 本次实测 | S36: 用例标题：未登录访问需登录页面
A37: QX-036 | B37: 权限体系 | C37: 未登录调用受保护接口-返回请先登录 | D37: 使用无会话的客户端，请求头带 X-Requested-With: XMLHttpRequest | E37: 1. 以 AJAX 方式请求受保护接口 2. 观察响应体 | F37: GET /home/leaves/datalist（无 Cookie，带 AJAX 头） | G37: 返回 code=404「请先登录」，不返回业务数据 | H37: 高 | I37: 无会话客户端 | J37: 测试计划 §4.3 未登录列；文案见 app/base/BaseController.php:90 | K37: 通过 | L37: 【(未登录)】POST /api/check/submit_check code=1 msg=请先登录 | M37: 原预期：返回 code=404「请先登录」；现预期：返回 code=1「请先登录」；修订原因：实测：未登录时 `apiError('请先登录')` 走的是 code=1，不是 404。用例把状态码写错，行为本身（拦截且不返回业务数据）符合预期。 | O37: 来源：case_results_qx.json | Q37: 本次实测 | S37: 用例标题：未登录调用受保护接口
A38: QX-037 | B38: 权限体系 | C38: 垂直越权-管理岗访问仅超管功能（数据还原） | D38: 已用管理岗账号登录 | E38: 1. 直接访问数据还原接口 2. 观察响应与库变化 | F38: URL: 备份还原页/接口 | G38: 被拦截，不执行还原动作 | H38: 高 | I38: 账号 fengcailing/<OA_USER_PWD> | J38: 测试计划 §4.3 #9（管理岗 ❌） | K38: 通过 | L38: 【fengcailing】POST /home/database/import http=200 code=405 msg=你没有权限,请联系管理员或者人事部 | O38: 来源：case_results_qx.json | Q38: 本次实测 | S38: 用例标题：垂直越权-管理岗访问数据还原
A39: QX-038 | B39: 权限体系 | C39: 垂直越权-非指定审批人调用审批动作接口 | D39: 已用业务岗账号登录，库中存在一条待审批且审批人不是该账号的单据 | E39: 1. 向审批动作接口发送请求，携带该单据 id 与通过参数 2. 查询单据 check_status 是否变化 | F39: POST /api/check/flow_check，单据 id + 通过 | G39: 被拦截；单据 check_status 不发生变化 | H39: 高 | I39: 账号 yucixin/<OA_USER_PWD> + 待审批单据 1 条 | J39: 测试计划 §4.3 #20（三档账号均 ❌）；对照 app/api/controller/Check.php:598 具备归属校验 | K39: 通过 | L39: 【yucixin】POST /api/check/flow_check check=1 action_id=1072 http=200 code=1 msg=您没权限审核该审批；check_status 1→1 未被改动=True | O39: 来源：case_results_qx.json | Q39: 本次实测 | R39: 非指定审批人 uid=5 审批 fengcailing(uid=4) 的待审批单（审批人=uid 1）→ 预期被拒且 check_status 不变 | S39: 用例标题：垂直越权-非指定审批人调用审批动作接口
A40: QX-039 | B40: 权限体系 | C40: 水平越权-业务岗查看他人请假单详情 | D40: 存在业务岗同事 yucixin 之外的他人请假单（如 fengcailing 提交） | E40: 1. 用 yucixin 登录 2. 请求他人请假单详情接口，携带他人单据 id 3. 观察响应体是否含他人单据内容 | F40: GET /home/leaves/view?id=<他人单据 id> | G40: 被拦截，不返回他人请假单内容 | H40: 高 | I40: 账号 yucixin/<OA_USER_PWD> + 他人请假单 1 条 | J40: 测试计划 §4.3 #15（业务岗 ❌）+ §4.2 越权用例；对应证据-03 | K40: 失败 | L40: 【testemp（已回收）】(见关联证据) 证据-03：「[读-攻击者 testemp ] GET /home/leaves/view?id=1002 -> HTTP 200 看到受害者事由原文=True」（testmin 亦可达）—— 预期『被拦截，不返回他人请假单内容』未达成 | O40: 证据-03（水平越权，严重 B）｜来源：case_results_qx.json | Q40: 据既有证据回填 | S40: 用例标题：水平越权-业务岗查看他人请假单详情
A41: QX-040 | B41: 权限体系 | C41: 水平越权-业务岗编辑他人请假单 | D41: 存在他人请假单，且其 id 已知 | E41: 1. 用 yucixin 登录 2. 向请假保存接口提交他人单据 id + 修改后的内容 3. 查询该单据字段是否被改写 | F41: POST /home/leaves/add，id=<他人单据 id>，reason=被篡改 | G41: 被拦截；他人单据内容不变 | H41: 高 | I41: 账号 yucixin/<OA_USER_PWD> + 他人请假单 1 条 | J41: 测试计划 §4.3 #16（业务岗 ❌）；对应证据-03 | K41: 失败 | L41: 【testemp（已回收）】(见关联证据) 证据-03：「[改-攻击者 testemp ] POST /home/leaves/add?id=1002 -> code=0 操作成功」+「[受害者回看] 事由已被改写=True」—— 他人单据内容被静默改写 | O41: 证据-03（水平越权，严重 B）｜来源：case_results_qx.json | Q41: 据既有证据回填 | S41: 用例标题：水平越权-业务岗编辑他人请假单
A42: QX-041 | B42: 权限体系 | C42: 水平越权-业务岗删除他人请假单 | D42: 存在他人请假单，且其 id 已知 | E42: 1. 用 yucixin 登录 2. 请求删除他人请假单 3. 查询该单据 delete_time | F42: DELETE /home/leaves/del，ids=<他人单据 id> | G42: 被拦截；他人单据 delete_time 保持 0 | H42: 高 | I42: 账号 yucixin/<OA_USER_PWD> + 他人请假单 1 条 | J42: 测试计划 §4.3 #17（业务岗 ❌）+ §4.2 越权用例 | K42: 失败 | L42: 【testemp（已回收）】(见关联证据) 证据-03：「[删] leaves 模块 单号 1002 —— 攻击者 testemp（code=0 操作成功，软删）」；且软删后该记录**仍被列表列出**（delete_time 过滤未生效） | O42: 证据-03（水平越权，严重 B）｜来源：case_results_qx.json | Q42: 据既有证据回填 | S42: 用例标题：水平越权-业务岗删除他人请假单
A43: QX-042 | B43: 权限体系 | C43: 水平越权-业务岗查看他人加班单 | D43: 存在他人加班单，且其 id 已知 | E43: 1. 用 yucixin 登录 2. 请求他人加班单详情 3. 观察响应体 | F43: GET /home/overtimes/view?id=<他人单据 id> | G43: 被拦截，不返回他人加班单内容 | H43: 高 | I43: 账号 yucixin/<OA_USER_PWD> + 他人加班单 1 条 | J43: 测试计划 §4.3 #15 同类；四个单据控制器结构一致（Leaves/Overtimes/Trips/Outs） | K43: 失败 | L43: 【testemp（已回收）】(见关联证据) 证据-03：overtimes 模块「[读-攻击者 testemp ] view?id=1002 -> 看到受害者事由原文=True」 | O43: 证据-03（水平越权，严重 B）｜来源：case_results_qx.json | Q43: 据既有证据回填 | S43: 用例标题：水平越权-业务岗查看他人加班单
A44: QX-043 | B44: 权限体系 | C44: 水平越权-业务岗查看他人出差单 | D44: 存在他人出差单，且其 id 已知 | E44: 1. 用 yucixin 登录 2. 请求他人出差单详情 3. 观察响应体 | F44: GET /home/trips/view?id=<他人单据 id> | G44: 被拦截，不返回他人出差单内容 | H44: 高 | I44: 账号 yucixin/<OA_USER_PWD> + 他人出差单 1 条 | J44: 测试计划 §4.3 #15 同类；对应证据-03 | K44: 失败 | L44: 【testemp（已回收）】(见关联证据) 证据-03：trips 模块「[读-攻击者 testemp ] view?id=1002 -> 看到受害者事由原文=True」 | O44: 证据-03（水平越权，严重 B）｜来源：case_results_qx.json | Q44: 据既有证据回填 | S44: 用例标题：水平越权-业务岗查看他人出差单
A45: QX-044 | B45: 权限体系 | C45: 水平越权-业务岗查看他人外出单 | D45: 存在他人外出单，且其 id 已知 | E45: 1. 用 yucixin 登录 2. 请求他人外出单详情 3. 观察响应体 | F45: GET /home/outs/view?id=<他人单据 id> | G45: 被拦截，不返回他人外出单内容 | H45: 高 | I45: 账号 yucixin/<OA_USER_PWD> + 他人外出单 1 条 | J45: 测试计划 §4.3 #15 同类；对应证据-03 | K45: 失败 | L45: 【testemp（已回收）】(见关联证据) 证据-03：outs 模块「[读-攻击者 testemp ] view?id=1002 -> 看到受害者事由原文=True」 | O45: 证据-03（水平越权，严重 B）｜来源：case_results_qx.json | Q45: 据既有证据回填 | S45: 用例标题：水平越权-业务岗查看他人外出单
A46: QX-045 | B46: 权限体系 | C46: 水平越权对照-本人查看本人请假单 | D46: yucixin 本人已提交请假单，且其 id 已知 | E46: 1. 用 yucixin 登录 2. 请求本人请假单详情 3. 观察响应体 | F46: GET /home/leaves/view?id=<本人单据 id> | G46: 正常返回本人单据内容（本用例是对照：证明越权用例的失败不是接口本身不可用） | H46: 高 | I46: 账号 yucixin/<OA_USER_PWD> + 本人请假单 1 条 | J46: 测试计划 §2.1 UI 对照法；对照设计用于排除「接口整体不可用」这一竞争假设 | K46: 通过 | L46: 【testemp（已回收）】(见关联证据) 证据-03：「[受害者自查] view -> HTTP 200 含事由原文=True」—— 本人可正常查看本人单据，**对照成立**：上面 QX-039~044 的失败不是『接口整体不可用』，而是**缺归属校验** | O46: 证据-03（对照组本身即通过）｜来源：case_results_qx.json | Q46: 据既有证据回填 | S46: 用例标题：水平越权对照-本人查看本人请假单
A47: QX-046 | B47: 权限体系 | C47: 水平越权-业务岗撤回他人请假单 | D47: 存在他人处于待审批状态的请假单 | E47: 1. 用 yucixin 登录 2. 请求撤回他人单据 3. 查询该单据 check_status | F47: 撤回接口，id=<他人单据 id> | G47: 被拦截；他人单据 check_status 不变为已撤回 | H47: 高 | I47: 账号 yucixin/<OA_USER_PWD> + 他人待审批单据 1 条 | J47: 测试计划 §4.3 #22（三档账号均 ❌）；反证见 app/api/controller/Check.php:598 具备归属校验 | K47: 通过 | L47: 【yucixin】POST /api/check/flow_check check=3 action_id=1072 http=200 code=1 msg=你没权限操作；check_status 1→1 未被改动=True | O47: 来源：case_results_qx.json | Q47: 本次实测 | R47: 业务岗 uid=5 撤回他人 uid=4 的请假单 → 预期被拒且 check_status 不变为 4（已撤回） | S47: 用例标题：水平越权-业务岗撤回他人请假单
A48: QX-047 | B48: 权限体系 | C48: 水平越权-站内消息越权操作他人收件箱状态 | D48: 构造一条 testmin 发给 yucixin 的消息；攻击者与其同岗同级 | E48: 1. 攻击者登录 2. 对他人收件记录调用消息状态接口，分别尝试移入垃圾箱与星标 3. 查询 oa_msg 对应字段 | F48: DELETE /home/message/check，ids=<他人收件 id>，type=2 / type=5 | G48: 被拦截；他人消息的 delete_time / is_star 不被改写 | H48: 高 | I48: 账号 testemp/<OA_USER_PWD> + oa_msg 记录 1 条 | J48: 对应证据-05；模块位于 $not_check 白名单（app/base/BaseController.php:115），不走 RBAC | K48: 失败 | L48: 【testemp（已回收）】(见关联证据) 证据-05 缺陷一：「DELETE /home/message/check {type:2, ids:1000} -> code=0 操作成功」，回读 oa_msg.id=1000 的 delete_time 已被改写（受害者收件箱不再可见该消息）；type=5 星标同样成功（is_star=1）—— 预期『被拦截，delete_time/is_star 不被改写』未达成 | O48: 证据-05 缺陷一（严重 B）｜来源：case_results_qx.json | Q48: 据既有证据回填 | S48: 用例标题：水平越权-站内消息越权操作他人收件箱状态
A49: QX-048 | B49: 权限体系 | C49: 水平越权-站内消息越权删除他人发件与草稿 | D49: 存在他人发件记录，且其 id 已知 | E49: 1. 攻击者登录 2. 请求删除他人发件记录 3. 查询 oa_message.delete_time | F49: DELETE /home/message/del，ids=<他人发件 id> | G49: 被拦截；他人发件记录 delete_time 保持 0 | H49: 高 | I49: 账号 testemp/<OA_USER_PWD> + oa_message 记录 1 条 | J49: 对应证据-05；同一文件内 view/read/reply/resend/add 均有归属校验，本接口缺失 | K49: 失败 | L49: 【testemp（已回收）】(见关联证据) 证据-05 缺陷二：Message.php:349-359 的 del() 「MessageList::where(['id'=>$val])->update([...])」无任何归属条件，实测攻击者可删他人发件/草稿。（用例原文写『查询 oa_message.delete_time』，实际表名为 oa_msg —— 属用例表述笔误，已在此更正） | O49: 证据-05 缺陷二（严重 B）｜来源：case_results_qx.json | Q49: 据既有证据回填 | S49: 用例标题：水平越权-站内消息越权删除他人发件与草稿
A50: QX-049 | B50: 权限体系 | C50: API授权-业务岗调用员工数据接口 | D50: 已用业务岗账号登录 | E50: 1. 请求 /api/index/get_employee 2. 观察响应体是否含员工敏感字段 | F50: GET /api/index/get_employee | G50: 被拦截，不返回员工数据；若返回全量员工（含手机号）则为缺陷 | H50: 高 | I50: 账号 yucixin/<OA_USER_PWD> | J50: 测试计划 §4.3 #30（⚠️ 预期被拦截但疑似缺陷）+ §11 候选缺陷 C2 | K50: 通过 | L50: 【yucixin】GET /api/index/get_employee code=0 msg= n=102；含 mobile 非空 102/102 条 | M50: 原预期：被拦截，不返回员工数据；若返回全量员工（含手机号）则为缺陷；现预期：按设计放行：业务岗可获取员工数据（含手机号）；修订原因：本条沿用**已撤回**的缺陷候选 C2 的处置：UI 对照法证明业务岗在 /user/user/index 企业员工页界面上本来就展示手机号列 → 对该角色属设计如此。真正的问题是**零权限账号**也能取得同一份数据（102 条含 mobile），该问题已由证据-01/证据-02（app/api/BaseController 缺 RBAC）覆盖，不重复记。 | O50: 来源：case_results_qx.json | Q50: 本次实测 | S50: 用例标题：API授权-业务岗调用员工数据接口（预期已修订）
A51: QX-050 | B51: 权限体系 | C51: API授权-业务岗调用员工导入接口 | D51: 已用业务岗账号登录 | E51: 1. 请求 /api/import/import_admin 2. 观察响应 | F51: POST /api/import/import_admin | G51: 被拦截，不执行导入 | H51: 高 | I51: 账号 yucixin/<OA_USER_PWD> | J51: 测试计划 §4.3 #31（⚠️）+ §11 候选缺陷 C3 | K51: 通过 | L51: 【yucixin】POST /api/import/import_admin code=1 msg=该操作只能是超级管理员有权限操作 | O51: 来源：case_results_qx.json | Q51: 本次实测 | S51: 用例标题：API授权-业务岗调用员工导入接口
A52: QX-051 | B52: 权限体系 | C52: API授权-业务岗调用数据导出接口 | D52: 已用业务岗账号登录 | E52: 1. 请求 /api/export/excel 2. 观察是否返回导出文件 | F52: GET /api/export/excel | G52: 被拦截，不返回导出内容 | H52: 高 | I52: 账号 yucixin/<OA_USER_PWD> | J52: 测试计划 §4.3 #32（⚠️）+ §11 候选缺陷 C3 | K52: 通过 | L52: 【yucixin】POST /api/export/excel http=500 code=None（未出现 405 → 无节点参与比对） | M52: 原预期：被拦截，不返回导出内容；现预期：无对应权限节点；实测参数缺失/记录不存在时返回 HTTP 500；修订原因：实测并已在上一阶段撤回缺陷候选 C3：oa_admin_rule 中**不存在** export 节点，RBAC 无可校验项；该接口是薪资详情页导入组件的正常调用。另发现：oa_salary 为空时 $detail 为 null，$detail['month_time'] 触发 500。 | N52: 业务层未做参数兜底：空载荷 POST 返回 HTTP 500 而非参数校验错误。与 Export.php:343 / Map.php:108 / Check.php:385,467 同源（PHP 8 未定义数组键警告被 ThinkPHP 升级为 ErrorException 后无人捕获） | O52: 来源：case_results_qx.json | Q52: 本次实测 | S52: 用例标题：API授权-业务岗调用数据导出接口（预期已修订）
A53: QX-052 | B53: 权限体系 | C53: API授权-未登录调用定位接口 | D53: 使用无会话的干净客户端 | E53: 1. 请求 /api/map/getLocation（不带 Cookie） 2. 观察状态码与响应体 | F53: GET /api/map/getLocation（无 Cookie） | G53: 被拦截；若返回 HTTP 500 或业务数据，则属未授权可访问，应记录为缺陷 | H53: 高 | I53: 无会话客户端 | J53: 测试计划 §4.3 + §11 候选缺陷 C1 | K53: 失败 | L53: 【(未登录)】GET /api/map/getLocation **未被拦截** http=500 code=None body=<!DOCTYPE html> <html> <head> <meta charset="U | N53: 业务层未做参数兜底：空载荷 POST 返回 HTTP 500 而非参数校验错误。与 Export.php:343 / Map.php:108 / Check.php:385,467 同源（PHP 8 未定义数组键警告被 ThinkPHP 升级为 ErrorException 后无人捕获） | O53: 来源：case_results_qx.json | Q53: 本次实测 | S53: 用例标题：API授权-未登录调用定位接口
A54: QX-053 | B54: 权限体系 | C54: API授权-未登录调用提交审批接口 | D54: 使用无会话的干净客户端 | E54: 1. 向提交审批接口发送请求 2. 观察响应 | F54: POST /api/check/submit_check（无 Cookie） | G54: 被拦截，返回请先登录，不产生任何单据 | H54: 高 | I54: 无会话客户端 | J54: 测试计划 §4.3 未登录列；API 侧仅校验登录（app/api/BaseController::checkLogin） | K54: 通过 | L54: 【(未登录)】POST /api/check/submit_check code=1 msg=请先登录 | O54: 来源：case_results_qx.json | Q54: 本次实测 | S54: 用例标题：API授权-未登录调用提交审批
A55: QX-054 | B55: 权限体系 | C55: API授权-会话超时后调用接口 | D55: 存在一个 last_login_time 距当前超过 10 小时的会话 | E55: 1. 构造超时会话（或等待） 2. 发起任意受保护请求 3. 观察响应 | F55: 受保护接口（携带超时会话 Cookie） | G55: 会话被判超时，跳转登录页或返回请先登录，不返回业务数据 | H55: 中 | I55: 测试账号 1 个（可改 last_login_time 构造） | J55: 超时阈值与判定见 app/base/BaseController.php:104-108（36000 秒）。注意 API 模块共用同一套会话 | K55: 失败 | L55: 【testmin】把 last_login_time 前移 36001 秒后，先调 /api/index/get_department 与 get_position、再访问 /home/role/index home 页面：HTTP 302 Location=/home/login/index.html（跳转登录页=符合预期）；/api 接口 get_department：HTTP 200 code=0 msg= n=15（**仍返回业务数据，未判超时**）；get_position：HTTP 200 code=0 msg= n=3（**仍返回业务数据，未判超时**） | N55: 缺陷一（严重 A）：app/api/BaseController 缺失 4 道闸门中的 3 道 —— 见 证据-01 | O55: 本条失败与**已归档缺陷一（证据-01 §c）同源**，不另立新缺陷：证据-01 §c 已实测「置 last_login_time=now-40000s → 页面 302 跳登录、/api/index/get_employee 仍返回 code=0 记录数=103」；本条用另一账号、另两个只读端点（get_department / get_position）独立复现同一现象，进一步坐实根因：app/api/BaseController::checkLogin() 只判断 Session::has()，不含超时/锁屏/强制改密/权限检查。｜来源：case_results_perm.json | Q55: 本次实测 | S55: 用例标题：API授权-会话超时后调用接口
A56: QX-055 | B56: 权限体系 | C56: 权限缓存-改角色后权限生效性验证 | D56: 已用超管账号登录；目标账号已访问过系统（缓存 RulesSrc<uid> 已生成） | E56: 1. 记录目标账号当前可访问的页面集合 2. 超管修改其角色权限并保存 3. **不清缓存**，目标账号再次访问变更的页面 4. 记录是否即时生效 | F56: 变更：新增/移除 1 个权限节点 | G56: 明确记录权限变更的生效行为（即时/需等缓存过期），作为结论写入报告；若为缓存导致则注明 36000s 有效期与清理方式 | H56: 中 | I56: 账号 admin/<OA_ADMIN_PWD> + 目标角色账号 | J56: 测试计划 §9 风险 #3、§1 权限缓存失效验证；缓存实现见 extend/systematic/Systematic.php:55-56 | K56: 通过 | L56: 【admin】记录权限变更的生效行为（授权/回收各一次，均含清缓存对照） 角色组权限变更（授权 / 回收）**保存后即时生效**，无需额外操作、也无需等待；机制依据（读源码，非推断）：clear_cache($key) → think\Cache::clear() 无 $tag 形参、File::clear() 亦无参且直接 rmdir 整个缓存目录 ⇒ 传入的 $key 被忽略，任何一次 clear_cache() 都是**全量清空**，故角色保存时 adminRules 必然一并失效；推论：源码中 Role.php:90-91 只写 adminMenu/MobileRules 与 Rule.php、Module.php、Position.php 写 adminRules 的差异**不产生行为差异**；双向对照：授权后 code 0（放行）、回收后 code 405（拦截），清缓存前后结果均不变 | O56: 来源：case_results_perm.json | Q56: 本次实测 | S56: 用例标题：权限缓存-改角色后权限生效性验证
A57: SP-001 | B57: 审批流 | C57: 请假单-正常提交 | D57: 已用业务岗账号登录 | E57: 1. 打开「我的假勤-请假」 2. 填写完整请假信息 3. 提交 4. 查看我申请的列表 | F57: 请假类型：事假；时长：1 天；起止时间：次日 09:00~18:00；事由：用例测试 | G57: 提交成功；单据生成且状态为待审批；oa_leaves 新增记录，admin_id 为当前账号 | H57: 高 | I57: 账号 yucixin/<OA_USER_PWD> | J57: 测试计划 §4.3 #13（业务岗 ✅） | K57: 通过 | L57: 【yucixin】POST /home/leaves/add + POST /api/check/submit_check 建单 code=0 id=1126；提交 code=0；oa_leaves.check_status=1（审批中）；admin_id=5 | O57: 来源：case_results_sp.json | Q57: 本次实测 | R57: 「提交」按「建单 + 提交审批」完整路径执行（本系统两动作分离）
A58: SP-002 | B58: 审批流 | C58: 请假单-必填项为空提交 | D58: 已用业务岗账号登录 | E58: 1. 打开请假表单 2. 清空事由/时间等必填项 3. 提交 | F58: 必填项留空 | G58: 提交被拒绝并给出明确的必填校验提示；不生成单据 | H58: 高 | I58: 账号 yucixin/<OA_USER_PWD> | J58: 测试计划 §4.2 异常用例 | K58: 失败 | L58: 【yucixin】POST /home/leaves/add（必填项全空） 未按预期拒绝：code=0 msg=操作成功；新增 1 条脏记录（已清理） | O58: 来源：case_results_sp.json | P58: **本条的缺陷归属（2026-09-19 评审定）**：查实但不单列缺陷，记入 04_缺陷报告「未单列观察项」表（观察-06）。理由 —— 与 BUG-15（批量导入按钮对业务岗可见、接口拒绝）同属「界面与接口的边界不一致」：界面侧 lay-verify=required 拦住了，接口侧没拦。后果是提交人名下多出一条内容为空的草稿单，本人即可删除，**不影响他人数据、不绕过任何安全控制、不涉及越权**，属数据卫生问题，定级会落到轻微（E）而非一般；故按「查实但不报」留档，不占用缺陷编号，但如实记录在案，避免「漏报」与「多报」两种失真。与 BUG-18 不并：那条是「状态校验缺失」（终态数据可被改写），本条是「必填项校验缺失」（新建时字段未校验），成因与后果都不同。受影响接口：POST /home/leaves/add（假勤四模块的 add 走同一套 home 控制器写法） | Q58: 本次实测 | R58: 必填项为空提交应被服务端拒绝；UI 侧 lay-verify=required 仅拦客户端
A59: SP-003 | B59: 审批流 | C59: 请假单-结束时间早于开始时间 | D59: 已用业务岗账号登录 | E59: 1. 打开请假表单 2. 开始时间填 18:00、结束时间填 09:00（同一天） 3. 提交 | F59: 开始：次日 18:00；结束：次日 09:00 | G59: 提交被拒绝并提示结束时间不得早于开始时间；不生成单据 | H59: 高 | I59: 账号 yucixin/<OA_USER_PWD> | J59: 测试计划 §4.2 异常用例 | K59: 通过 | L59: 【yucixin】POST /home/leaves/add（结束早于开始） 被拒绝：code=1 msg=「结束时间不能小于开始时间」；未生成单据 | O59: 来源：case_results_sp.json | Q59: 本次实测
A60: SP-004 | B60: 审批流 | C60: 请假单-请假时长 0.5 天（边界） | D60: 已用业务岗账号登录 | E60: 1. 提交一张 0.5 天的请假单 2. 查看时长字段与列表显示 | F60: 时长：0.5 天（上午半天） | G60: 提交成功；时长按 0.5 天存储与展示，不出现小数精度或取整错误 | H60: 中 | I60: 账号 yucixin/<OA_USER_PWD> | J60: 测试计划 §4.2 边界值（请假 0.5 天） | K60: 通过 | L60: 【yucixin】POST /home/leaves/add（duration=0.5） 建单成功 id=1128；oa_leaves.duration=0.5（decimal(10,1)，无精度丢失） | O60: 来源：case_results_sp.json | Q60: 本次实测
A61: SP-005 | B61: 审批流 | C61: 请假单-请假时长 999 天（边界） | D61: 已用业务岗账号登录 | E61: 1. 提交一张跨 999 天的请假单 2. 观察系统响应 | F61: 时长：999 天 | G61: 系统按规则处理（允许则正常入参并显示，不允许则给出上限提示）；不出现 500 或数据错乱 | H61: 中 | I61: 账号 yucixin/<OA_USER_PWD> | J61: 测试计划 §4.2 边界值（请假 999 天） | K61: 通过 | L61: 【yucixin】POST /home/leaves/add（duration=999） 系统允许并正确入库：id=1129 duration=999.0 check_status=0；无 500、无数据错乱 | O61: 来源：case_results_sp.json | Q61: 本次实测 | R61: 系统对超长时长未设上限，按「允许则正常入参」判通过
A62: SP-006 | B62: 审批流 | C62: 请假单-提交后状态为待审批 | D62: 已提交一张请假单 | E62: 1. 查看该单据详情 2. 查看列表中的状态列 | F62: 无 | G62: 状态显示为待审批；oa_leaves.check_status 为待审批对应值 | H62: 高 | I62: 账号 yucixin/<OA_USER_PWD> + 本人请假单 1 条 | J62: 测试计划 §4.2 状态流转 | K62: 通过 | L62: 【yucixin】GET 单据详情 + oa_leaves.check_status id=1126 check_status=1（审批中）—— 等待审批人处理，与「待审批」同义 | O62: 来源：case_results_sp.json | Q62: 本次实测 | R62: 用例写「待审批」，系统状态枚举值为 1「审批中」，语义一致
A63: SP-007 | B63: 审批流 | C63: 请假单-本人可查看详情 | D63: 已提交一张请假单，其 id 已知 | E63: 1. 用提交人账号请求该单据详情 2. 核对关键字段 | F63: GET /home/leaves/view?id=<本人单据 id> | G63: 正常返回单据详情，字段与提交内容一致 | H63: 高 | I63: 账号 yucixin/<OA_USER_PWD> + 本人请假单 1 条 | J63: 测试计划 §4.3 #14（业务岗 ✅）；同时作为 QX-039 的对照 | K63: 通过 | L63: 【yucixin】GET /home/leaves/view?id=1126 HTTP 200；页面含提交时填写的事由「【用例数据】SP-001-正常提交」；字段与提交内容一致 | O63: 来源：case_results_sp.json | Q63: 本次实测
A64: SP-008 | B64: 审批流 | C64: 请假单-本人撤回待审批单据 | D64: 存在本人处于待审批状态的请假单 | E64: 1. 在列表中对待审批单据执行撤回 2. 查看状态 | F64: 撤回目标：本人待审批请假单 | G64: 撤回成功；状态变为已撤回；该单据不再出现在审批人待办列表 | H64: 高 | I64: 账号 yucixin/<OA_USER_PWD> + 本人待审批单据 1 条 | J64: 测试计划 §4.3 #21（✅）+ §1 撤回（check_status=4） | K64: 通过 | L64: 【yucixin】POST /api/check/flow_check check=3（撤回） 撤回前 check_status=1；撤回 code=0；撤回后 check_status=4（已撤回）；审批人待办命中数=0 | O64: 来源：case_results_sp.json | Q64: 本次实测
A65: SP-009 | B65: 审批流 | C65: 请假单-已通过单据不可撤回 | D65: 存在本人已审批通过的请假单 | E65: 1. 对该单据执行撤回 2. 观察响应 | F65: 撤回目标：本人已通过请假单 | G65: 撤回被拒绝并给出明确提示；单据状态保持已通过 | H65: 中 | I65: 账号 yucixin/<OA_USER_PWD> + 本人已通过单据 1 条 | J65: 测试计划 §4.2 状态流转 | K65: 失败 | L65: 【yucixin】POST /api/check/flow_check check=3（对已通过单据撤回） 状态 2 → 撤回 code=0 msg=「操作成功」→ 状态 4（期望被拒且保持 2） | N65: BUG-18 状态机只在界面层校验（一般 C）—— 本条是同一根因在审批模块的表现 | O65: 证据-13｜来源：case_results_sp.json | Q65: 本次实测 | R65: 审批动作应校验单据当前状态。**这条例外排除了「归属校验」这一解释**：BUG-08 的对照组 QX-046 已实测「撤回收他人单据被拒（你没权限操作）」，说明 check=3 分支**有**归属校验，缺的是**状态**校验 —— 对**自己名下、已审批通过**的单据撤回，接口直接放行。界面侧的通知/操作区按状态渲染，故正常操作路径碰不到该场景
A66: SP-010 | B66: 审批流 | C66: 请假单-审批通过后状态回写 | D66: 存在一张待审批请假单，当前账号是其指定审批人 | E66: 1. 用审批人账号在待审批列表中打开该单据 2. 执行通过 3. 查询 oa_leaves.check_status 与审批时间字段 | F66: 审批动作：通过 | G66: 状态变为已通过；审批时间/审批人被正确回写；申请人可见最新状态 | H66: 高 | I66: 账号 fengcailing/<OA_USER_PWD> + 待审批单据 1 条 | J66: 测试计划 §2 数据校验（审批状态回写） | K66: 通过 | L66: 【yucixin】POST /api/check/flow_check check=1（审批人 fengcailing） 审批 code=0；check_status=2（审批通过）；申请人可见审批历史：由「风采铃」于 2026-09-19 00:27 审核通过 | O66: 来源：case_results_sp.json | P66: 自由审批模式下单据表 check_time=0、check_last_uid=「」均不回写（Check.php 更新单据的 field 列表未含 check_time；check_last_uid 仅在固定多级流程回写）；已查 app/home/view 视图与 gougu 前端 JS 均未消费这两列，无用户可见影响 | Q66: 本次实测 | R66: 状态已回写；审批人/审批时间记于 oa_flow_record 并在详情页审批时间线展示
A67: SP-011 | B67: 审批流 | C67: 请假单-审批驳回后状态与驳回意见 | D67: 存在一张待审批请假单，当前账号是其指定审批人 | E67: 1. 在待审批列表中打开该单据 2. 填写驳回意见后驳回 3. 用申请人账号查看 | F67: 审批动作：驳回；意见：用例测试驳回 | G67: 状态变为已驳回；驳回意见被保存且申请人可见 | H67: 高 | I67: 账号 fengcailing/<OA_USER_PWD> + 待审批单据 1 条 | J67: 测试计划 §1 审批流-驳回；§4.2 状态流转 | K67: 通过 | L67: 【yucixin】POST /api/check/flow_check check=2（驳回，含意见） 驳回 code=0；check_status=3（审批不通过）；申请人取审批历史得 2 条，含「审核拒绝 / 用例测试驳回」 | O67: 来源：case_results_sp.json | Q67: 本次实测 | R67: 详情页审批时间线由 JS 取 /api/check/get_flow_nodes 渲染，按该接口判定可见性
A68: SP-012 | B68: 审批流 | C68: 请假单-驳回后重新提交 | D68: 存在一张已被驳回的本人请假单 | E68: 1. 用申请人账号编辑该单据 2. 修改内容后重新提交 3. 查看状态 | F68: 修改事由后重新提交 | G68: 重新提交成功，状态回到待审批；审批链按规则重新流转 | H68: 中 | I68: 账号 yucixin/<OA_USER_PWD> + 已驳回单据 1 条 | J68: 测试计划 §4.2 状态流转（已驳回→重新提交） | K68: 通过 | L68: 【yucixin】POST /home/leaves/add（带 id 编辑）+ submit_check 重新提交 重提前 check_status=3；编辑 code=0；重新提交 code=0；重提后 check_status=1（审批中）；新审批链 flow_step=1 条 | O68: 来源：case_results_sp.json | Q68: 本次实测
A69: SP-013 | B69: 审批流 | C69: 加班单-正常提交 | D69: 已用业务岗账号登录 | E69: 1. 打开「我的假勤-加班」 2. 填写完整加班信息 3. 提交 | F69: 加班时长：2 小时；时间：次日 19:00~21:00；事由：用例测试 | G69: 提交成功；oa_overtimes 新增记录且状态为待审批 | H69: 高 | I69: 账号 yucixin/<OA_USER_PWD> | J69: 测试计划 §4.3 #13 同类（加班模块） | K69: 通过 | L69: 【yucixin】POST /home/overtimes/add 加班单建单成功 id=1014；oa_overtimes.check_status=0（待提交审批）；归属人 admin_id=5 | O69: 来源：case_results_sp.json | Q69: 本次实测 | R69: 用例的「提交」=建单动作；后续「审批」用例各自独立建单并 submit_check
A70: SP-014 | B70: 审批流 | C70: 加班单-结束时间早于开始时间 | D70: 已用业务岗账号登录 | E70: 1. 打开加班表单 2. 开始时间填 21:00、结束时间填 19:00 3. 提交 | F70: 开始：次日 21:00；结束：次日 19:00 | G70: 提交被拒绝并提示时间区间不合法；不生成单据 | H70: 高 | I70: 账号 yucixin/<OA_USER_PWD> | J70: 测试计划 §4.2 异常用例 | K70: 通过 | L70: 【yucixin】POST /home/overtimes/add（结束早于开始） 被拒绝：code=1 msg=「结束时间不能小于开始时间」；未生成单据 | O70: 来源：case_results_sp.json | Q70: 本次实测
A71: SP-015 | B71: 审批流 | C71: 加班单-审批通过 | D71: 存在一张待审批加班单，当前账号是其指定审批人 | E71: 1. 在待审批列表中通过该加班单 2. 查询单据状态 | F71: 审批动作：通过 | G71: 状态变为已通过；加班时长字段与提交值一致 | H71: 中 | I71: 账号 fengcailing/<OA_USER_PWD> + 待审批加班单 1 条 | J71: 测试计划 §2 数据校验 | K71: 通过 | L71: 【yucixin】POST /api/check/flow_check check=1（加班单） 审批 code=0；check_status=2（审批通过）；duration=2.0 与提交值一致 | O71: 来源：case_results_sp.json | Q71: 本次实测
A72: SP-016 | B72: 审批流 | C72: 出差单-正常提交 | D72: 已用业务岗账号登录 | E72: 1. 打开「我的假勤-出差」 2. 填写完整出差信息 3. 提交 | F72: 出差地：用例测试地；起止：次日至次日+2；事由：用例测试 | G72: 提交成功；oa_trips 新增记录且状态为待审批 | H72: 高 | I72: 账号 yucixin/<OA_USER_PWD> | J72: 测试计划 §4.3 #13 同类（出差模块） | K72: 通过 | L72: 【yucixin】POST /home/trips/add 出差单建单成功 id=1014；oa_trips.check_status=0（待提交审批）；归属人 admin_id=5 | O72: 来源：case_results_sp.json | Q72: 本次实测 | R72: 用例的「提交」=建单动作；后续「审批」用例各自独立建单并 submit_check
A73: SP-017 | B73: 审批流 | C73: 出差单-审批驳回 | D73: 存在一张待审批出差单，当前账号是其指定审批人 | E73: 1. 在待审批列表中驳回该出差单 2. 填写驳回意见 3. 用申请人账号查看 | F73: 审批动作：驳回；意见：用例测试驳回 | G73: 状态变为已驳回；驳回意见对申请人可见 | H73: 中 | I73: 账号 fengcailing/<OA_USER_PWD> + 待审批出差单 1 条 | J73: 测试计划 §1 审批流-驳回 | K73: 通过 | L73: 【yucixin】POST /api/check/flow_check check=2（出差单驳回） 驳回 code=0；check_status=3（审批不通过）；申请人取审批历史得 2 条，含「审核拒绝 / 用例测试驳回」 | O73: 来源：case_results_sp.json | Q73: 本次实测 | R73: 与 SP-011 同口径：详情页审批时间线由 JS 渲染，按接口判定可见性
A74: SP-018 | B74: 审批流 | C74: 外出单-正常提交 | D74: 已用业务岗账号登录 | E74: 1. 打开「我的假勤-外出」 2. 填写完整外出信息 3. 提交 | F74: 外出时间：次日 14:00~17:00；事由：用例测试 | G74: 提交成功；oa_outs 新增记录且状态为待审批 | H74: 高 | I74: 账号 yucixin/<OA_USER_PWD> | J74: 测试计划 §4.3 #13 同类（外出模块） | K74: 通过 | L74: 【yucixin】POST /home/outs/add 外出单建单成功 id=1014；oa_outs.check_status=0（待提交审批）；归属人 admin_id=5 | O74: 来源：case_results_sp.json | Q74: 本次实测 | R74: 用例的「提交」=建单动作；后续「审批」用例各自独立建单并 submit_check
A75: SP-019 | B75: 审批流 | C75: 外出单-审批通过 | D75: 存在一张待审批外出单，当前账号是其指定审批人 | E75: 1. 在待审批列表中通过该外出单 2. 查询单据状态 | F75: 审批动作：通过 | G75: 状态变为已通过并正确回写 | H75: 中 | I75: 账号 fengcailing/<OA_USER_PWD> + 待审批外出单 1 条 | J75: 测试计划 §2 数据校验 | K75: 通过 | L75: 【yucixin】POST /api/check/flow_check check=1（外出单） 审批 code=0；check_status=2（审批通过）并正确回写 check_time=0 | O75: 来源：case_results_sp.json | Q75: 本次实测
A76: SP-020 | B76: 审批流 | C76: 全流程-多级审批逐级流转 | D76: 已配置两级审批流程的请假类型 | E76: 1. 申请人提交请假单 2. 第一级审批人通过 3. 观察是否流转到第二级 4. 第二级审批人通过 | F76: 审批流程：两级（check_step_sort 依次为 1、2） | G76: 第一级通过后单据流转至第二级，第二级待办中出现该单据；两级均通过后状态才变为已通过 | H76: 高 | I76: 账号 yucixin + 两级审批人各 1 | J76: 测试计划 §1 多级审批（check_step_sort + flow_list） | K76: 通过 | L76: 【yucixin】submit_check → 第一级 flow_check(node=2) → 第二级 flow_check 审批链 flow_step=2 级；第一级通过后 check_status=1 且当前审批人转为 admin(uid=1)；第二级通过后 check_status=2（审批通过） | O76: 来源：case_results_sp.json | Q76: 本次实测
A77: SP-021 | B77: 审批流 | C77: 多级审批-第一级通过后流转到第二级 | D77: 存在两级审批流程，且已有单据处于第一级待审批 | E77: 1. 第一级审批人通过 2. 用第二级审批人账号查看待我审批列表 3. 查询单据当前审批步骤字段 | F77: 无 | G77: 第二级待办中出现该单据；单据当前步骤字段指向第二级 | H77: 高 | I77: 账号 yucixin + 两级审批人各 1 | J77: 测试计划 §1 多级审批 | K77: 通过 | L77: 【yucixin】第一级通过后查 oa_leaves 步骤字段 + admin 待办 第一级通过后 check_status=1；check_step_sort=1；当前审批人 check_uids=1（已指向第二级 admin）；历史审批人 check_history_uids=4 | O77: 来源：case_results_sp.json | Q77: 本次实测
A78: SP-022 | B78: 审批流 | C78: 多级审批-中间级驳回后流程终止 | D78: 存在两级审批流程，且单据已流转到第二级 | E78: 1. 第二级审批人驳回 2. 查询单据状态与后续待办 | F78: 审批动作：第二级驳回 | G78: 单据状态变为已驳回；不再产生后续待办；第一级审批记录仍保留在审批历史中 | H78: 高 | I78: 账号 yucixin + 两级审批人各 1 | J78: 测试计划 §1 多级审批 + 审批历史记录 | K78: 通过 | L78: 【yucixin】第二级审批人驳回 驳回 code=0；check_status=3（审批不通过）；后续待办数=0；审批记录 2→3 条（第一级记录保留） | O78: 来源：case_results_sp.json | Q78: 本次实测
A79: SP-023 | B79: 审批流 | C79: 会签-全部通过才通过 | D79: 已配置会签（check_types=1）的审批流程，含 2 名以上审批人 | E79: 1. 申请人提交单据 2. 会签人中前几位分别通过 3. 查询在所有人通过前的单据状态 4. 最后一位通过后再次查询 | F79: check_types=1（会签全过） | G79: 全部通过前状态保持审批中；最后一位通过后状态才变为已通过 | H79: 高 | I79: 账号 yucixin + 会签审批人 2 名以上 | J79: 测试计划 §1 会签/或签（check_types：1=会签全过） | K79: 通过 | L79: 【admin(1) → fengcailing(4)】POST /api/check/submit_check(flow_id=20，不带 check_uids) + 两次 POST /api/check/flow_check 提交后：oa_leaves.check_status=1、check_uids=1,4、生成 1 级步骤（check_types=1 会签）；第1位(admin)通过后：check_status=1（仍审批中）、check_uids=4（剩第2位）、本级审批记录 1 条；第2位(fengcailing)通过后：check_status=2（已通过）、check_uids=(空) | O79: 来源：case_results_sp_flow.json | Q79: 本次实测 | R79: 会签（check_types=1）需凑满本级人数才流转，判据 app/api/controller/Check.php:414
A80: SP-024 | B80: 审批流 | C80: 会签-一人驳回则整体驳回 | D80: 已配置会签（check_types=1）且单据处于会签中 | E80: 1. 其中一位会签人驳回 2. 查询单据状态 3. 查看其余会签人的待办 | F80: 审批动作：其中一人驳回 | G80: 单据状态变为已驳回；其余会签人的待办不再需要处理（或标记为已终止） | H80: 高 | I80: 账号 yucixin + 会签审批人 2 名以上 | J80: 测试计划 §1 会签（1=会签全过） | K80: 通过 | L80: 【admin(1) → fengcailing(4)】POST /api/check/flow_check（check=1 通过 → check=2 驳回） 第1位通过后：check_status=1、check_uids=4、第2位(id=4)有待办=True；第2位驳回后：check_status=3（不通过）、check_uids=(空)、第2位待办=False（已终止） | O80: 来源：case_results_sp_flow.json | Q80: 本次实测 | R80: 会签中一人驳回的整体状态与其余人待办终止（Check.php:527 起的驳回分支；只有 check_role==5 才走 :542 的回退逻辑，本级 check_role=4 时直接置终态 3）
A81: SP-025 | B81: 审批流 | C81: 或签-任一人通过即通过 | D81: 已配置或签（check_types=2）的审批流程，含 2 名以上审批人 | E81: 1. 申请人提交单据 2. 其中一位审批人通过 3. 查询单据状态 | F81: check_types=2（或签任一） | G81: 该审批人通过后单据即变为已通过，无需其余审批人处理 | H81: 高 | I81: 账号 yucixin + 或签审批人 2 名以上 | J81: 测试计划 §1 会签/或签（check_types：2=或签任一） | K81: 通过 | L81: 【admin(1)（第2位 fengcailing 全程未审批）】POST /api/check/submit_check(flow_id=21) + 一次 POST /api/check/flow_check(check=1) 或签流程 2 级（第1级 或签 uid=1,4；第2级 uid=1）；提交后 check_status=1、check_uids=1,4；仅第1位(admin)通过后：check_step_sort 0→1、check_status=1（仍审批中）、check_uids=1（= 第2级审批人）、第1级审批记录仅 1 条、落选者(id=4)待办 True→False | M81: 设计原文「该审批人通过后单据即变为已通过」**只在或签处于末级时成立**。本次实测用两级或签流程（第1级或签 2 人 / 第2级 1 人），故第1级任一人通过后单据**进入第2级**：check_status 仍=1（审批中）、check_step_sort 0→1、check_uids 改写为第2级审批人「1」。判据「任一人通过即流转、不等其余人」与设计一致，故记通过，仅修订措辞（「变为已通过」→「进入下一级」）。 | O81: 来源：case_results_sp_flow.json | Q81: 本次实测 | R81: 或签（check_types=2）任一人通过即流转，判据 app/api/controller/Check.php:414
A82: SP-026 | B82: 审批流 | C82: 或签-其余审批人待办自动取消 | D82: 或签流程中，已有一人通过使单据变为已通过 | E82: 1. 用另一位或签审批人账号查看待我审批列表 2. 观察该单据是否仍在待办中 | F82: 无 | G82: 该单据不再出现在其余审批人的待办列表中，避免重复审批 | H82: 中 | I82: 账号 或签审批人各 1 | J82: 测试计划 §1 或签（2=或签任一） | K82: 通过 | L82: 【admin(1)（落选者 fengcailing 未审批）】POST /api/check/submit_check(flow_id=21) + 一次 POST /api/check/flow_check(check=1)；并用 /home/approve 的同一判据查待办 通过前：落选者(id=4)对本单有待办=True、其跨模块待办总数=31；或签第1位(admin)通过后：本单待办=False、跨模块待办总数=30（差 1）；同时 check_status=1（**仍审批中**，非结束）、check_step_sort=1、check_uids=1、第1级审批记录 1 条 | M82: 设计原文「已有一人通过使单据变为已通过」同上：两级流程下一人通过后单据仍在审批中（check_status=1）。「其余审批人待办自动取消」这一预期成立（落选者待办 True→False，跨模块待办 31→30），故记通过；仅将「变为已通过」修订为「进入下一级」。 | O82: 来源：case_results_sp_flow.json | Q82: 本次实测 | R82: 或签其余审批人待办自动取消（Check.php:411-413 把通过者移出 check_uids，:430 或签流转时把 check_uids 整体改写为下一级审批人；本流程刻意配了第 2 级，用以区分「落选取消」与「整单结束」）
A83: SP-027 | B83: 审批流 | C83: 审批动作-非指定审批人调用审批接口 | D83: 存在一张待审批单据，其指定审批人不包含当前账号 | E83: 1. 用非指定审批人账号向审批动作接口发送通过请求 2. 查询单据状态 | F83: POST /api/check/flow_check，单据 id + 通过 | G83: 被拦截；单据状态不发生变化；不产生审批记录 | H83: 高 | I83: 账号 yucixin/<OA_USER_PWD> + 他人待审批单据 1 条 | J83: 测试计划 §4.3 #20（三档账号均 ❌）；对照 app/api/controller/Check.php:598 具备归属校验 | K83: 通过 | L83: 【admin】POST /api/check/flow_check check=1（非指定审批人 admin） 被拦截 code=1 msg=「您没权限审核该审批」；单据状态 1→1 未变化；审批记录 1→1 条（零痕迹） | O83: 证据-03 ④（同一系统内审批动作有归属校验 vs 四模块 CRUD 没有）｜来源：case_results_sp.json | Q83: 本次实测
A84: SP-028 | B84: 审批流 | C84: 待我审批列表-仅列出本人待审批单据 | D84: 系统中存在多名审批人的待审批单据 | E84: 1. 用某审批人账号打开待我审批列表 2. 核对每条单据的当前审批人 | F84: GET /home/approve/checklist | G84: 列表仅包含当前账号作为当前步骤审批人的单据；不含他人待办、不含已处理单据 | H84: 高 | I84: 账号 fengcailing/<OA_USER_PWD> + 多条待审批单据 | J84: 测试计划 §4.3 #18（管理岗 ✅） | K84: 通过 | L84: 【fengcailing】POST /home/approve/checklist?status=1（待我审批） 列表 27 条，与库中「check_uids 含 fengcailing(uid=4) 且 check_status<2」的 27 条一致；每条当前审批人均含本人，无他人待办、无已处理单据 | O84: 来源：case_results_sp.json | Q84: 本次实测
A85: SP-029 | B85: 审批流 | C85: 抄送-抄送人可见但不需审批 | D85: 已配置抄送（is_copy）的审批流程 | E85: 1. 申请人提交单据 2. 用抄送人账号查看抄送列表 3. 核对是否出现在待审批列表 | F85: 无 | G85: 抄送人可在抄送列表中看到该单据；不出现在待我审批列表，无需其处理 | H85: 中 | I85: 账号 yucixin + 抄送人 1 名 | J85: 测试计划 §1 抄送（is_copy） | K85: 通过 | L85: 【yucixin】submit_check(check_copy_uids=admin) + admin 查抄送列表/待办列表 提交 code=0；oa_leaves.check_copy_uids=1；抄送人 admin 的抄送列表中可见该单=True；待我审批列表中不出现=True | O85: 来源：case_results_sp.json | Q85: 本次实测
A86: SP-030 | B86: 审批流 | C86: 退回-审批人退回后回到申请人 | D86: 已配置退回（is_back）的审批流程，单据处于待审批 | E86: 1. 审批人执行退回 2. 用申请人账号查看单据状态 | F86: 审批动作：退回 | G86: 单据回到申请人处（状态为已退回/待修改）；申请人可修改后重新提交 | H86: 中 | I86: 账号 yucixin + 审批人 1 名 | J86: 测试计划 §1 退回（is_back） | K86: 通过 | L86: 【yucixin】审批人 check=2 退回 → 申请人改写后重新提交 退回 code=0；单据回到申请人（check_status=3 审批不通过）；申请人改写 code=0 后重新提交 code=0，状态回到 1（审批中） | O86: 来源：case_results_sp.json | Q86: 本次实测 | R86: 本系统「退回」与「驳回」同走 check=2 分支（Check.php），故落库状态同为 3「审批不通过」
A87: SP-031 | B87: 审批流 | C87: 审批历史记录-完整记录审批链 | D87: 存在一张经过多级审批（含一次驳回后重新提交）的单据 | E87: 1. 打开该单据详情 2. 查看审批历史区域 | F87: 无 | G87: 审批历史按时间顺序完整记录每一级审批人、动作、意见、时间；驳回后重新提交的历史也保留 | H87: 高 | I87: 账号 yucixin/<OA_USER_PWD> + 多级审批单据 1 条 | J87: 测试计划 §1 审批历史记录、§4.2 状态流转 | K87: 通过 | L87: 【yucixin】两级审批 + 驳回 + 重提后查看审批历史 审批历史 4 条（提交/玉辞心 → 审核通过/风采铃 → 审核拒绝/超级员工 → 提交/玉辞心），时间升序=True，每条均有审批人与时间；链路含驳回意见 | O87: 来源：case_results_sp.json | Q87: 本次实测 | R87: 驳回后重新提交的旧记录虽被软删，界面时间线仍完整展示（get_flow_nodes 不过滤 delete_time）
A88: SP-032 | B88: 审批流 | C88: 撤回-撤回后流程终止 | D88: 单据处于多级审批的第一级之后 | E88: 1. 用申请人账号撤回该单据 2. 查询单据状态 3. 查看审批人待办 | F88: 撤回目标：本人审批中单据 | G88: 状态变为已撤回；后续审批人待办中不再出现该单据；已产生的审批记录保留 | H88: 高 | I88: 账号 yucixin/<OA_USER_PWD> + 审批中单据 1 条 | J88: 测试计划 §1 撤回（check_status=4） | K88: 通过 | L88: 【yucixin】单据流转到第二级后由申请人撤回 撤回 code=0；check_status=4（已撤回）；第二级审批人待办命中数=0；审批记录 2→3 条（已产生的记录保留） | O88: 来源：case_results_sp.json | Q88: 本次实测
A89: SP-033 | B89: 审批流 | C89: 列表筛选-按状态筛选 | D89: 本人存在待审批、已通过、已驳回、已撤回各至少 1 条单据 | E89: 1. 打开我申请的列表 2. 依次按各状态筛选 3. 核对结果条数 | F89: 筛选条件：各状态值 | G89: 筛选结果与库中对应状态的本人单据条数一致；无跨状态串数据 | H89: 中 | I89: 账号 yucixin/<OA_USER_PWD> + 各状态单据各 1 条 | J89: 测试计划 §4.4 接口 12（/home/approve/mylist）；注意与证据-04 的参数错位问题区分——审批列表走 controller 正确路径 | K89: 通过 | L89: 【yucixin】POST /home/approve/mylist（按 status 筛选） 各状态筛选结果与库中本人单据条数逐项一致：待审批(check_status<2): 库81/接口81/越界0；已通过(check_status=2): 库24/接口24/越界0；已驳回/已撤回(check_status>2): 库26/接口26/越界0；无跨状态串数据、无他人数据 | O89: 来源：case_results_sp.json | Q89: 本次实测
A90: SP-034 | B90: 审批流 | C90: 列表分页-第二页数据正确 | D90: 本人单据数量超过一页（大于每页条数） | E90: 1. 打开我申请的列表 2. 翻到第二页 3. 核对数据不重复、不缺失 | F90: 页码：2；每页条数：默认值 | G90: 第二页返回剩余单据；与第一页无重复；总数与库中本人单据数一致 | H90: 中 | I90: 账号 yucixin/<OA_USER_PWD> + 单据数量超过一页 | J90: 测试计划 §1 列表分页；对照证据-04 记录的 home/leaves 分页参数失效问题 | K90: 失败 | L90: 【yucixin】POST /home/approve/mylist 逐页遍历（limit=10，共 14 页） 分页跨页重复/漏行：接口 count=131，逐页取回 14 页、去重后仅 128 条（少 3 条），重复项 [(('trips', '1014'), 1, 2), (('leaves', '1123'), 2, 3), (('overtimes', '1010'), 5, 6)]。根因——Approve::get_list() 收尾为「ORDER BY create_time DESC LIMIT offset,size」，只有 create_time 一个排序键且精度到秒；19 类单据 UNION 后同秒并列的记录在两次不同 OFFSET 查询里顺序不固定，并列组压在页边界时即重复出现并挤掉本应展示的记录。降序=True | N90: BUG-16（列表分页排序键不唯一致跨页重复/漏行，一般 C） | O90: 证据-11｜来源：case_results_sp.json | Q90: 本次实测 | R90: 分页基数按 /home/approve/* 的 19 类单据 UNION 口径统计，与接口同源；唯一键取 (table_name,id)，因各表 id 独立自增；逐页遍历以覆盖并列组压边界的场景
A91: SP-035 | B91: 审批流 | C91: 单据列表-他人单据不出现在本人列表 | D91: 系统中存在他人的请假/加班/出差/外出单据 | E91: 1. 用业务岗账号打开我的假勤各列表 2. 核对每条记录的归属人 | F91: 无 | G91: 列表中仅包含本人单据，不含他人单据（数据权限生效） | H91: 高 | I91: 账号 yucixin/<OA_USER_PWD> + 他人单据各 1 条 | J91: 测试计划 §1 数据权限（oa_data_auth）生效性 + §4.3 #14 | K91: 通过 | L91: 【yucixin】POST /oa/attendance/datalist（tab=1~4） 业务岗 yucixin 的「我的假勤」四个列表均只含本人单据：请假(tab=1): 库中本人91条，接口返回91条，他人0条；出差(tab=2): 库中本人9条，接口返回9条，他人0条；外出(tab=3): 库中本人9条，接口返回9条，他人0条；加班(tab=4): 库中本人9条，接口返回9条，他人0条 | O91: 来源：case_results_sp.json | P91: 另有 /home/{leaves,trips,outs,overtimes}/datalist 为全员可见的团队视图（源码无 admin_id 过滤），非「我的」列表，未计入本条判定 | Q91: 本次实测 | R91: 「我的假勤」= oa/attendance/datalist，源码显式按 admin_id 过滤
A92: HT-001 | B92: 合同管理 | C92: 销售合同-新增 | D92: 已用管理岗账号登录，具备合同新增权限 | E92: 1. 打开「合同管理-销售合同」 2. 点击新增，填写完整合同信息 3. 保存 4. 回到列表查看 | F92: 合同名称：用例测试销售合同A；对方单位：用例测试公司；金额：10000.00；起止日期：当日至次年同日；税点：6 | G92: 保存成功；oa_contract 新增记录且类型为销售合同；列表中可见 | H92: 高 | I92: 账号 fengcailing/<OA_USER_PWD> | J92: 测试计划 §4.3 #24（管理岗 ✅） | K92: 通过 | L92: 【fengcailing】POST /contract/contract/add → GET /contract/contract/datalist 建单 code=0 return_id=1098；oa_contract 落库 types=1（销售合同表-普通类型）cost=10000.00 is_tax=1 tax=6.00 起止=2026-09-19~2027-09-19 admin_id=4；列表中可见该合同=True | O92: 来源：case_results_ht.json | Q92: 本次实测
A93: HT-002 | B93: 合同管理 | C93: 销售合同-列表查看 | D93: 库中已有销售合同数据 | E93: 1. 打开销售合同列表 2. 观察列表字段与分页 | F93: 无 | G93: 正常展示销售合同列表，含合同名称、金额、状态、起止日期等关键字段；分页可用 | H93: 高 | I93: 账号 fengcailing/<OA_USER_PWD> + 销售合同数据 | J93: 测试计划 §4.3 #23（管理岗 ✅）、§4.5 合同测试数据 15~20 条 | K93: 通过 | L93: 【fengcailing】GET /contract/contract/datalist（第 1、2 页） 列表 count=1；目标合同 name/cost/code 与库中一致；interval_time=「2026-09-19 至 2027-09-19」覆盖库中起止 2026-09-19~2027-09-19；关键字段齐全（name/cost/status_name/interval_time/code/sign_time）；第 2 页取到 0 条（分页可用） | O93: 来源：case_results_ht.json | Q93: 本次实测
A94: HT-003 | B94: 合同管理 | C94: 销售合同-编辑 | D94: 库中存在一条销售合同，其 id 已知 | E94: 1. 打开该合同编辑页 2. 修改合同名称与金额 3. 保存 4. 重新打开详情核对 | F94: 名称改为：用例测试销售合同A-已改；金额改为：12000.00 | G94: 保存成功；详情显示修改后的值；oa_contract 对应字段已更新 | H94: 高 | I94: 账号 fengcailing/<OA_USER_PWD> + 销售合同 1 条 | J94: 测试计划 §4.3 #25（管理岗 ✅） | K94: 通过 | L94: 【fengcailing】POST /contract/contract/add（scene=edit）→ GET /contract/contract/view 编辑 code=0；oa_contract 由「【用例数据】用例测试销售合同A / 10000.00」更新为「【用例数据】用例测试销售合同A-已改 / 12000.00」；详情页已显示新名称与新金额 | O94: 来源：case_results_ht.json | Q94: 本次实测
A95: HT-004 | B95: 合同管理 | C95: 销售合同-删除 | D95: 已用超管账号登录；库中存在一条可删除的测试合同 | E95: 1. 在列表中对测试合同执行删除 2. 确认 3. 查询该合同 delete_time | F95: 删除目标：用例测试销售合同（专用测试数据） | G95: 删除成功，列表中不再显示；oa_contract.delete_time 变为非 0（软删除） | H95: 高 | I95: 账号 admin/<OA_ADMIN_PWD> + 测试合同 1 条 | J95: 测试计划 §4.3 #26（超管 ✅）；删除实现对应该表 delete_time 字段 | K95: 通过 | L95: 【admin】DELETE /contract/contract/del?id=1099 code=0；oa_contract.delete_time=1789749556（软删除，非物理删除）；列表中已不可见 | O95: 来源：case_results_ht.json | P95: Contract::del() 只判断了请求方法（request()->isDelete()），没有任何归属或权限校验 —— 任何已登录账号都能按 id 软删任意合同。归入 BUG-02「合同模块接口缺 RBAC 闸门」同族问题，不另开编号 | Q95: 本次实测
A96: HT-005 | B96: 合同管理 | C96: 销售合同-详情查看 | D96: 库中存在一条销售合同，其 id 已知 | E96: 1. 在列表中点击该合同进入详情 2. 核对各字段 | F96: 无 | G96: 详情正确展示全部字段，与库中数据一致；金额与日期格式正确 | H96: 中 | I96: 账号 fengcailing/<OA_USER_PWD> + 销售合同 1 条 | J96: 测试计划 §4.4 接口 18（合同详情） | K96: 通过 | L96: 【fengcailing】GET /contract/contract/view?id=1100 HTTP 200；详情页与库中数据逐项一致：名称/编码/金额(8888.88)/起止日期(2026-09-09~2027-07-16) 全部命中 | O96: 来源：case_results_ht.json | Q96: 本次实测 | R96: 金额按 decimal(15,2) 存储，页面回显 8888.88 无精度丢失
A97: HT-006 | B97: 合同管理 | C97: 采购合同-新增 | D97: 已用管理岗账号登录 | E97: 1. 打开「合同管理-采购合同」 2. 填写完整信息并保存 3. 回列表查看 | F97: 合同名称：用例测试采购合同A；对方单位：用例测试供应商；金额：5000.00；税点：13 | G97: 保存成功；记录类型为采购合同；列表中可见 | H97: 高 | I97: 账号 fengcailing/<OA_USER_PWD> | J97: 测试计划 §4.3 #24 + §4.5（采购合同） | K97: 通过 | L97: 【fengcailing】POST /contract/purchase/add → GET /contract/purchase/datalist 建单 code=0 return_id=1027；oa_purchase 落库 types=1（采购合同表-普通类型）cost=5000.00 admin_id=4；采购列表中可见 | O97: 来源：case_results_ht.json | Q97: 本次实测 | R97: 用例「测试数据」列写了「税点：13」，但 oa_purchase 表没有税点字段（对采购合同未建模税点），故本用例只核对有落库的字段
A98: HT-007 | B98: 合同管理 | C98: 采购合同-列表查看 | D98: 库中已有采购合同数据 | E98: 1. 打开采购合同列表 2. 观察列表内容 | F98: 无 | G98: 正常展示采购合同列表；销售与采购两类数据不串 | H98: 高 | I98: 账号 fengcailing/<OA_USER_PWD> + 采购合同数据 | J98: 测试计划 §4.3 #23 | K98: 通过 | L98: 【fengcailing】GET /contract/purchase/datalist + GET /contract/contract/datalist 采购列表 count=1 含目标合同，name/cost/code 与库一致（【用例数据】用例测试采购合同A / 5000.00 / HT-CASE-PU004）；销售列表 count=2 中不含任何采购合同 code（两类分属 oa_contract / oa_purchase 两张表） | O98: 来源：case_results_ht.json | Q98: 本次实测 | R98: 判重用 code 而非 id：两张表各自自增，id 不具跨表唯一性
A99: HT-008 | B99: 合同管理 | C99: 采购合同-编辑 | D99: 库中存在一条采购合同，其 id 已知 | E99: 1. 打开编辑页 2. 修改金额与备注 3. 保存并核对 | F99: 金额改为：5500.00 | G99: 保存成功；详情显示新值 | H99: 中 | I99: 账号 fengcailing/<OA_USER_PWD> + 采购合同 1 条 | J99: 测试计划 §4.3 #25 | K99: 通过 | L99: 【fengcailing】POST /contract/purchase/add（scene=edit）→ GET purchase/view 编辑 code=0；cost 5000.00→5500.00、备注已更新；详情页已显示新金额 | O99: 来源：case_results_ht.json | Q99: 本次实测
A100: HT-009 | B100: 合同管理 | C100: 采购合同-删除 | D100: 已用超管账号登录；库中存在测试用采购合同 | E100: 1. 列表中对测试采购合同执行删除 2. 查询 delete_time | F100: 删除目标：用例测试采购合同（专用测试数据） | G100: 删除成功；delete_time 变为非 0 | H100: 中 | I100: 账号 admin/<OA_ADMIN_PWD> + 测试采购合同 1 条 | J100: 测试计划 §4.3 #26 | K100: 通过 | L100: 【admin】DELETE /contract/purchase/del?id=1028 code=0；oa_purchase.delete_time=1789749559（软删除） | O100: 来源：case_results_ht.json | Q100: 本次实测
...

Sheet 统计汇总
A1: 勾股OA 6.1.2 —— 测试用例统计汇总
A2: 生成时间 | B2: 2026-09-19 02:28:01
A4: 【总体】
A5: 用例总数 | B5: =COUNTA('测试用例'!$A$2:$A$136) | C5: 公式统计，非硬编码
A6: 通过 | B6: =COUNTIF('测试用例'!$K$2:$K$136,"通过")
A7: 失败 | B7: =COUNTIF('测试用例'!$K$2:$K$136,"失败")
A8: 待执行 | B8: =COUNTIF('测试用例'!$K$2:$K$136,"待执行")
A9: 环境受限-范围外 | B9: =COUNTIF('测试用例'!$K$2:$K$136,"环境受限-范围外") | C9: 独立第四态，不与通过/失败混算
A10: 已执行（通过+失败） | B10: =$B$6+$B$7
A11: 执行率（已执行/总数） | B11: =IF($B$5=0,0,$B$10/$B$5) | C11: 未执行用例须逐条书面说明原因
A12: 通过率（含回填） | B12: =IF($B$10=0,0,$B$6/$B$10) | C12: 分母=已执行（通过+失败）；含 9 条「据既有证据回填」。⚠️ 该 9 条为 8 失败 + 1 通过，计入是**拉低**而非抬高通过率
A13: 通过率（仅本次实测） | B13: =IF(COUNTIFS('测试用例'!$Q$2:$Q$136,"本次实测")=0,0,COUNTIFS('测试用例'!$K$2:$K$136,"通过",'测试用例'!$Q$2:$Q$136,"本次实测")/COUNTIFS('测试用例'!$Q$2:$Q$136,"本次实测")) | C13: 分母=执行方式为「本次实测」的用例，剔除 9 条回填 —— 可信度分列的落点
A15: 【按执行方式】
A16: 本次实测 | B16: =COUNTIF('测试用例'!$Q$2:$Q$136,"本次实测")
A17: 据既有证据回填 | B17: =COUNTIF('测试用例'!$Q$2:$Q$136,"据既有证据回填")
A18: 未执行 | B18: =COUNTIF('测试用例'!$Q$2:$Q$136,"未执行")
A19: 合计（应=用例总数） | B19: =$B$16+$B$17+$B$18 | C19: 用于校验执行方式列无缺失/无非法值
A21: 【按模块】
A22: 权限体系
A23: 小计 | B23: =COUNTIF('测试用例'!$B$2:$B$136,"权限体系")
A24: 通过 | B24: =COUNTIFS('测试用例'!$B$2:$B$136,"权限体系",'测试用例'!$K$2:$K$136,"通过")
A25: 失败 | B25: =COUNTIFS('测试用例'!$B$2:$B$136,"权限体系",'测试用例'!$K$2:$K$136,"失败")
A26: 待执行 | B26: =COUNTIFS('测试用例'!$B$2:$B$136,"权限体系",'测试用例'!$K$2:$K$136,"待执行")
A27: 环境受限-范围外 | B27: =COUNTIFS('测试用例'!$B$2:$B$136,"权限体系",'测试用例'!$K$2:$K$136,"环境受限-范围外")
A28: 审批流
A29: 小计 | B29: =COUNTIF('测试用例'!$B$2:$B$136,"审批流")
A30: 通过 | B30: =COUNTIFS('测试用例'!$B$2:$B$136,"审批流",'测试用例'!$K$2:$K$136,"通过")
A31: 失败 | B31: =COUNTIFS('测试用例'!$B$2:$B$136,"审批流",'测试用例'!$K$2:$K$136,"失败")
A32: 待执行 | B32: =COUNTIFS('测试用例'!$B$2:$B$136,"审批流",'测试用例'!$K$2:$K$136,"待执行")
A33: 环境受限-范围外 | B33: =COUNTIFS('测试用例'!$B$2:$B$136,"审批流",'测试用例'!$K$2:$K$136,"环境受限-范围外")
A34: 合同管理
A35: 小计 | B35: =COUNTIF('测试用例'!$B$2:$B$136,"合同管理")
A36: 通过 | B36: =COUNTIFS('测试用例'!$B$2:$B$136,"合同管理",'测试用例'!$K$2:$K$136,"通过")
A37: 失败 | B37: =COUNTIFS('测试用例'!$B$2:$B$136,"合同管理",'测试用例'!$K$2:$K$136,"失败")
A38: 待执行 | B38: =COUNTIFS('测试用例'!$B$2:$B$136,"合同管理",'测试用例'!$K$2:$K$136,"待执行")
A39: 环境受限-范围外 | B39: =COUNTIFS('测试用例'!$B$2:$B$136,"合同管理",'测试用例'!$K$2:$K$136,"环境受限-范围外")
A40: 薪资管理
A41: 小计 | B41: =COUNTIF('测试用例'!$B$2:$B$136,"薪资管理")
A42: 通过 | B42: =COUNTIFS('测试用例'!$B$2:$B$136,"薪资管理",'测试用例'!$K$2:$K$136,"通过")
A43: 失败 | B43: =COUNTIFS('测试用例'!$B$2:$B$136,"薪资管理",'测试用例'!$K$2:$K$136,"失败")
A44: 待执行 | B44: =COUNTIFS('测试用例'!$B$2:$B$136,"薪资管理",'测试用例'!$K$2:$K$136,"待执行")
A45: 环境受限-范围外 | B45: =COUNTIFS('测试用例'!$B$2:$B$136,"薪资管理",'测试用例'!$K$2:$K$136,"环境受限-范围外")
A47: 【按优先级】
A48: 高 | B48: =COUNTIF('测试用例'!$H$2:$H$136,"高")
A49: 中 | B49: =COUNTIF('测试用例'!$H$2:$H$136,"中")
A50: 低 | B50: =COUNTIF('测试用例'!$H$2:$H$136,"低")
